{"v":"4.8.0","meta":{"g":"LottieFiles AE ","a":"","k":"","d":"","tc":""},"fr":29.9700012207031,"ip":5.00000020365417,"op":82.0000033399285,"w":280,"h":700,"nm":"Lottie_rocket","ddd":1,"assets":[],"layers":[{"ddd":0,"ind":1,"ty":3,"nm":"Null 20","sr":1,"ks":{"o":{"a":0,"k":0,"ix":11},"r":{"a":0,"k":0,"ix":10},"p":{"a":0,"k":[140,153,0],"ix":2},"a":{"a":0,"k":[0,0,0],"ix":1},"s":{"a":0,"k":[134,134,100],"ix":6}},"ao":0,"ip":0,"op":150.000006109625,"st":0,"bm":0},{"ddd":1,"ind":2,"ty":4,"nm":"Layer 9 Outlines 2","parent":16,"sr":1,"ks":{"o":{"a":0,"k":100,"ix":11},"rx":{"a":0,"k":0,"ix":8},"ry":{"a":0,"k":0,"ix":9},"rz":{"a":0,"k":0,"ix":10},"or":{"a":0,"k":[0,0,0],"ix":7},"p":{"a":0,"k":[-48.957,93.371,0],"ix":2},"a":{"a":0,"k":[33.239,70.278,0],"ix":1},"s":{"a":1,"k":[{"i":{"x":[0.667,0.667,0.667],"y":[1,1,1]},"o":{"x":[0.333,0.333,0.333],"y":[0,0,0]},"t":17,"s":[0,0,100]},{"i":{"x":[0.667,0.667,0.667],"y":[1,1,1]},"o":{"x":[0.333,0.333,0.333],"y":[0,0,0]},"t":27,"s":[75,75,100]},{"t":36.0000014663101,"s":[0,0,100]}],"ix":6}},"ao":0,"shapes":[{"ty":"gr","it":[{"ind":0,"ty":"sh","ix":1,"ks":{"a":0,"k":{"i":[[0,21.584],[17.118,0],[0,-21.585],[-17.119,0]],"o":[[0,21.584],[17.118,0],[0,-21.585],[-17.133,0]],"v":[[0.001,-39.07],[-30.997,0],[0.001,39.07],[30.997,0]],"c":true},"ix":2},"nm":"Path 1","mn":"ADBE Vector Shape - Group","hd":false},{"ty":"st","c":{"a":0,"k":[0,0,0,1],"ix":3},"o":{"a":0,"k":100,"ix":4},"w":{"a":0,"k":1,"ix":5},"lc":2,"lj":2,"bm":0,"nm":"Stroke 1","mn":"ADBE Vector Graphic - Stroke","hd":false},{"ty":"tr","p":{"a":0,"k":[33.497,71.054],"ix":2},"a":{"a":0,"k":[0,0],"ix":1},"s":{"a":0,"k":[100,100],"ix":3},"r":{"a":0,"k":0,"ix":6},"o":{"a":0,"k":100,"ix":7},"sk":{"a":0,"k":0,"ix":4},"sa":{"a":0,"k":0,"ix":5},"nm":"Transform"}],"nm":"Group 1","np":2,"cix":2,"bm":0,"ix":1,"mn":"ADBE Vector Group","hd":false},{"ty":"gr","it":[{"ind":0,"ty":"sh","ix":1,"ks":{"a":0,"k":{"i":[[0,21.584],[17.118,0],[0,-21.585],[-17.119,0]],"o":[[0,21.584],[17.118,0],[0,-21.585],[-17.133,0]],"v":[[0.001,-39.07],[-30.997,0],[0.001,39.07],[30.997,0]],"c":true},"ix":2},"nm":"Path 1","mn":"ADBE Vector Shape - Group","hd":false},{"ty":"fl","c":{"a":0,"k":[1,1,1,1],"ix":4},"o":{"a":0,"k":100,"ix":5},"r":1,"bm":0,"nm":"Fill 1","mn":"ADBE Vector Graphic - Fill","hd":false},{"ty":"tr","p":{"a":0,"k":[33.497,71.054],"ix":2},"a":{"a":0,"k":[0,0],"ix":1},"s":{"a":0,"k":[100,100],"ix":3},"r":{"a":0,"k":0,"ix":6},"o":{"a":0,"k":100,"ix":7},"sk":{"a":0,"k":0,"ix":4},"sa":{"a":0,"k":0,"ix":5},"nm":"Transform"}],"nm":"Group 2","np":4,"cix":2,"bm":0,"ix":2,"mn":"ADBE Vector Group","hd":false}],"ip":15.0000006109625,"op":39.0000015885026,"st":-17.0000006924242,"bm":0},{"ddd":0,"ind":3,"ty":4,"nm":"Layer 9 Outlines 4","parent":16,"sr":1,"ks":{"o":{"a":0,"k":100,"ix":11},"r":{"a":0,"k":0,"ix":10},"p":{"a":0,"k":[51.043,88.552,0],"ix":2},"a":{"a":0,"k":[33.239,70.278,0],"ix":1},"s":{"a":1,"k":[{"i":{"x":[0.667,0.667,0.667],"y":[1,1,1]},"o":{"x":[0.333,0.333,0.333],"y":[0,0,0]},"t":41,"s":[0,0,100]},{"i":{"x":[0.667,0.667,0.667],"y":[1,1,1]},"o":{"x":[0.333,0.333,0.333],"y":[0,0,0]},"t":51,"s":[50,50,100]},{"t":60.0000024438501,"s":[0,0,100]}],"ix":6}},"ao":0,"shapes":[{"ty":"gr","it":[{"ind":0,"ty":"sh","ix":1,"ks":{"a":0,"k":{"i":[[0,21.584],[17.118,0],[0,-21.585],[-17.119,0]],"o":[[0,21.584],[17.118,0],[0,-21.585],[-17.133,0]],"v":[[0.001,-39.07],[-30.997,0],[0.001,39.07],[30.997,0]],"c":true},"ix":2},"nm":"Path 1","mn":"ADBE Vector Shape - Group","hd":false},{"ty":"st","c":{"a":0,"k":[0,0,0,1],"ix":3},"o":{"a":0,"k":100,"ix":4},"w":{"a":0,"k":1,"ix":5},"lc":2,"lj":2,"bm":0,"nm":"Stroke 1","mn":"ADBE Vector Graphic - Stroke","hd":false},{"ty":"tr","p":{"a":0,"k":[33.497,71.054],"ix":2},"a":{"a":0,"k":[0,0],"ix":1},"s":{"a":0,"k":[100,100],"ix":3},"r":{"a":0,"k":0,"ix":6},"o":{"a":0,"k":100,"ix":7},"sk":{"a":0,"k":0,"ix":4},"sa":{"a":0,"k":0,"ix":5},"nm":"Transform"}],"nm":"Group 1","np":2,"cix":2,"bm":0,"ix":1,"mn":"ADBE Vector Group","hd":false},{"ty":"gr","it":[{"ind":0,"ty":"sh","ix":1,"ks":{"a":0,"k":{"i":[[0,21.584],[17.118,0],[0,-21.585],[-17.119,0]],"o":[[0,21.584],[17.118,0],[0,-21.585],[-17.133,0]],"v":[[0.001,-39.07],[-30.997,0],[0.001,39.07],[30.997,0]],"c":true},"ix":2},"nm":"Path 1","mn":"ADBE Vector Shape - Group","hd":false},{"ty":"fl","c":{"a":0,"k":[1,1,1,1],"ix":4},"o":{"a":0,"k":100,"ix":5},"r":1,"bm":0,"nm":"Fill 1","mn":"ADBE Vector Graphic - Fill","hd":false},{"ty":"tr","p":{"a":0,"k":[33.497,71.054],"ix":2},"a":{"a":0,"k":[0,0],"ix":1},"s":{"a":0,"k":[100,100],"ix":3},"r":{"a":0,"k":0,"ix":6},"o":{"a":0,"k":100,"ix":7},"sk":{"a":0,"k":0,"ix":4},"sa":{"a":0,"k":0,"ix":5},"nm":"Transform"}],"nm":"Group 2","np":4,"cix":2,"bm":0,"ix":2,"mn":"ADBE Vector Group","hd":false}],"ip":39.0000015885026,"op":63.0000025660426,"st":7.00000028511585,"bm":0},{"ddd":0,"ind":4,"ty":4,"nm":"Layer 9 Outlines 3","parent":16,"sr":1,"ks":{"o":{"a":0,"k":100,"ix":11},"r":{"a":0,"k":0,"ix":10},"p":{"a":0,"k":[-48.957,100.052,0],"ix":2},"a":{"a":0,"k":[33.239,70.278,0],"ix":1},"s":{"a":1,"k":[{"i":{"x":[0.667,0.667,0.667],"y":[1,1,1]},"o":{"x":[0.333,0.333,0.333],"y":[0,0,0]},"t":65,"s":[0,0,100]},{"i":{"x":[0.667,0.667,0.667],"y":[1,1,1]},"o":{"x":[0.333,0.333,0.333],"y":[0,0,0]},"t":75,"s":[75,75,100]},{"t":84.0000034213901,"s":[0,0,100]}],"ix":6}},"ao":0,"shapes":[{"ty":"gr","it":[{"ind":0,"ty":"sh","ix":1,"ks":{"a":0,"k":{"i":[[0,21.584],[17.118,0],[0,-21.585],[-17.119,0]],"o":[[0,21.584],[17.118,0],[0,-21.585],[-17.133,0]],"v":[[0.001,-39.07],[-30.997,0],[0.001,39.07],[30.997,0]],"c":true},"ix":2},"nm":"Path 1","mn":"ADBE Vector Shape - Group","hd":false},{"ty":"st","c":{"a":0,"k":[0,0,0,1],"ix":3},"o":{"a":0,"k":100,"ix":4},"w":{"a":0,"k":1,"ix":5},"lc":2,"lj":2,"bm":0,"nm":"Stroke 1","mn":"ADBE Vector Graphic - Stroke","hd":false},{"ty":"tr","p":{"a":0,"k":[33.497,71.054],"ix":2},"a":{"a":0,"k":[0,0],"ix":1},"s":{"a":0,"k":[100,100],"ix":3},"r":{"a":0,"k":0,"ix":6},"o":{"a":0,"k":100,"ix":7},"sk":{"a":0,"k":0,"ix":4},"sa":{"a":0,"k":0,"ix":5},"nm":"Transform"}],"nm":"Group 1","np":2,"cix":2,"bm":0,"ix":1,"mn":"ADBE Vector Group","hd":false},{"ty":"gr","it":[{"ind":0,"ty":"sh","ix":1,"ks":{"a":0,"k":{"i":[[0,21.584],[17.118,0],[0,-21.585],[-17.119,0]],"o":[[0,21.584],[17.118,0],[0,-21.585],[-17.133,0]],"v":[[0.001,-39.07],[-30.997,0],[0.001,39.07],[30.997,0]],"c":true},"ix":2},"nm":"Path 1","mn":"ADBE Vector Shape - Group","hd":false},{"ty":"fl","c":{"a":0,"k":[1,1,1,1],"ix":4},"o":{"a":0,"k":100,"ix":5},"r":1,"bm":0,"nm":"Fill 1","mn":"ADBE Vector Graphic - Fill","hd":false},{"ty":"tr","p":{"a":0,"k":[33.497,71.054],"ix":2},"a":{"a":0,"k":[0,0],"ix":1},"s":{"a":0,"k":[100,100],"ix":3},"r":{"a":0,"k":0,"ix":6},"o":{"a":0,"k":100,"ix":7},"sk":{"a":0,"k":0,"ix":4},"sa":{"a":0,"k":0,"ix":5},"nm":"Transform"}],"nm":"Group 2","np":4,"cix":2,"bm":0,"ix":2,"mn":"ADBE Vector Group","hd":false}],"ip":63.0000025660426,"op":87.0000035435827,"st":31.0000012626559,"bm":0},{"ddd":0,"ind":5,"ty":4,"nm":"Layer 9 Outlines 5","parent":16,"sr":1,"ks":{"o":{"a":0,"k":100,"ix":11},"r":{"a":0,"k":0,"ix":10},"p":{"a":0,"k":[51.043,88.552,0],"ix":2},"a":{"a":0,"k":[33.239,70.278,0],"ix":1},"s":{"a":1,"k":[{"i":{"x":[0.667,0.667,0.667],"y":[1,1,1]},"o":{"x":[0.333,0.333,0.333],"y":[0,0,0]},"t":89,"s":[0,0,100]},{"i":{"x":[0.667,0.667,0.667],"y":[1,1,1]},"o":{"x":[0.333,0.333,0.333],"y":[0,0,0]},"t":99,"s":[50,50,100]},{"t":108.00000439893,"s":[0,0,100]}],"ix":6}},"ao":0,"shapes":[{"ty":"gr","it":[{"ind":0,"ty":"sh","ix":1,"ks":{"a":0,"k":{"i":[[0,21.584],[17.118,0],[0,-21.585],[-17.119,0]],"o":[[0,21.584],[17.118,0],[0,-21.585],[-17.133,0]],"v":[[0.001,-39.07],[-30.997,0],[0.001,39.07],[30.997,0]],"c":true},"ix":2},"nm":"Path 1","mn":"ADBE Vector Shape - Group","hd":false},{"ty":"st","c":{"a":0,"k":[0,0,0,1],"ix":3},"o":{"a":0,"k":100,"ix":4},"w":{"a":0,"k":1,"ix":5},"lc":2,"lj":2,"bm":0,"nm":"Stroke 1","mn":"ADBE Vector Graphic - Stroke","hd":false},{"ty":"tr","p":{"a":0,"k":[33.497,71.054],"ix":2},"a":{"a":0,"k":[0,0],"ix":1},"s":{"a":0,"k":[100,100],"ix":3},"r":{"a":0,"k":0,"ix":6},"o":{"a":0,"k":100,"ix":7},"sk":{"a":0,"k":0,"ix":4},"sa":{"a":0,"k":0,"ix":5},"nm":"Transform"}],"nm":"Group 1","np":2,"cix":2,"bm":0,"ix":1,"mn":"ADBE Vector Group","hd":false},{"ty":"gr","it":[{"ind":0,"ty":"sh","ix":1,"ks":{"a":0,"k":{"i":[[0,21.584],[17.118,0],[0,-21.585],[-17.119,0]],"o":[[0,21.584],[17.118,0],[0,-21.585],[-17.133,0]],"v":[[0.001,-39.07],[-30.997,0],[0.001,39.07],[30.997,0]],"c":true},"ix":2},"nm":"Path 1","mn":"ADBE Vector Shape - Group","hd":false},{"ty":"fl","c":{"a":0,"k":[1,1,1,1],"ix":4},"o":{"a":0,"k":100,"ix":5},"r":1,"bm":0,"nm":"Fill 1","mn":"ADBE Vector Graphic - Fill","hd":false},{"ty":"tr","p":{"a":0,"k":[33.497,71.054],"ix":2},"a":{"a":0,"k":[0,0],"ix":1},"s":{"a":0,"k":[100,100],"ix":3},"r":{"a":0,"k":0,"ix":6},"o":{"a":0,"k":100,"ix":7},"sk":{"a":0,"k":0,"ix":4},"sa":{"a":0,"k":0,"ix":5},"nm":"Transform"}],"nm":"Group 2","np":4,"cix":2,"bm":0,"ix":2,"mn":"ADBE Vector Group","hd":false}],"ip":87.0000035435826,"op":111.000004521123,"st":55.0000022401959,"bm":0},{"ddd":1,"ind":6,"ty":4,"nm":"Layer 12 Outlines","parent":16,"sr":1,"ks":{"o":{"a":0,"k":100,"ix":11},"rx":{"a":0,"k":0,"ix":8},"ry":{"a":0,"k":0,"ix":9},"rz":{"a":0,"k":0,"ix":10},"or":{"a":0,"k":[0,0,0],"ix":7},"p":{"a":0,"k":[-5.758,157.635,0],"ix":2},"a":{"a":0,"k":[80.373,190.428,0],"ix":1},"s":{"a":0,"k":[74.428,74.428,74.428],"ix":6}},"ao":0,"shapes":[{"ty":"gr","it":[{"ind":0,"ty":"sh","ix":1,"ks":{"a":0,"k":{"i":[[4.649,2.533],[0.587,0.092],[4.448,-8.172],[4.68,0.726],[-0.524,-0.279],[-5.019,9.205]],"o":[[-0.51,-0.278],[3.15,3.552],[-4.465,8.171],[0.401,0.448],[4.635,2.533],[5.022,-9.207]],"v":[[7.438,-17.648],[5.77,-18.188],[3.73,1.939],[-12.087,14.542],[-10.728,15.656],[6.757,3.591]],"c":true},"ix":2},"nm":"Path 1","mn":"ADBE Vector Shape - Group","hd":false},{"ty":"st","c":{"a":0,"k":[0,0,0,1],"ix":3},"o":{"a":0,"k":100,"ix":4},"w":{"a":0,"k":1,"ix":5},"lc":2,"lj":2,"bm":0,"nm":"Stroke 1","mn":"ADBE Vector Graphic - Stroke","hd":false},{"ty":"tr","p":{"a":0,"k":[126.914,256.092],"ix":2},"a":{"a":0,"k":[0,0],"ix":1},"s":{"a":0,"k":[100,100],"ix":3},"r":{"a":0,"k":0,"ix":6},"o":{"a":0,"k":100,"ix":7},"sk":{"a":0,"k":0,"ix":4},"sa":{"a":0,"k":0,"ix":5},"nm":"Transform"}],"nm":"Group 1","np":2,"cix":2,"bm":0,"ix":1,"mn":"ADBE Vector Group","hd":false},{"ty":"gr","it":[{"ind":0,"ty":"sh","ix":1,"ks":{"a":0,"k":{"i":[[4.649,2.533],[0.587,0.092],[4.448,-8.172],[4.68,0.726],[-0.524,-0.279],[-5.019,9.205]],"o":[[-0.51,-0.278],[3.15,3.552],[-4.465,8.171],[0.401,0.448],[4.635,2.533],[5.022,-9.207]],"v":[[7.438,-17.648],[5.77,-18.188],[3.73,1.939],[-12.087,14.542],[-10.728,15.656],[6.757,3.591]],"c":true},"ix":2},"nm":"Path 1","mn":"ADBE Vector Shape - Group","hd":false},{"ty":"fl","c":{"a":0,"k":[0,0,0,1],"ix":4},"o":{"a":0,"k":100,"ix":5},"r":1,"bm":0,"nm":"Fill 1","mn":"ADBE Vector Graphic - Fill","hd":false},{"ty":"tr","p":{"a":0,"k":[126.914,256.092],"ix":2},"a":{"a":0,"k":[0,0],"ix":1},"s":{"a":0,"k":[100,100],"ix":3},"r":{"a":0,"k":0,"ix":6},"o":{"a":0,"k":100,"ix":7},"sk":{"a":0,"k":0,"ix":4},"sa":{"a":0,"k":0,"ix":5},"nm":"Transform"}],"nm":"Group 2","np":4,"cix":2,"bm":0,"ix":2,"mn":"ADBE Vector Group","hd":false},{"ty":"gr","it":[{"ind":0,"ty":"sh","ix":1,"ks":{"a":0,"k":{"i":[[0,0],[32.948,-2.286]],"o":[[-1.668,-39.651],[0,0]],"v":[[27.348,98.138],[-27.348,-95.852]],"c":false},"ix":2},"nm":"Path 1","mn":"ADBE Vector Shape - Group","hd":false},{"ty":"st","c":{"a":0,"k":[0,0,0,1],"ix":3},"o":{"a":0,"k":100,"ix":4},"w":{"a":0,"k":1,"ix":5},"lc":2,"lj":2,"bm":0,"nm":"Stroke 1","mn":"ADBE Vector Graphic - Stroke","hd":false},{"ty":"tr","p":{"a":0,"k":[106.524,100.901],"ix":2},"a":{"a":0,"k":[0,0],"ix":1},"s":{"a":0,"k":[100,100],"ix":3},"r":{"a":0,"k":0,"ix":6},"o":{"a":0,"k":100,"ix":7},"sk":{"a":0,"k":0,"ix":4},"sa":{"a":0,"k":0,"ix":5},"nm":"Transform"}],"nm":"Group 3","np":2,"cix":2,"bm":0,"ix":3,"mn":"ADBE Vector Group","hd":false},{"ty":"gr","it":[{"ind":0,"ty":"sh","ix":1,"ks":{"a":0,"k":{"i":[[1.792,13.176],[0.015,0.14],[0,0],[0,0],[-23.617,2.194],[0,-30.739],[-9.221,-51.899],[0,0],[-0.015,-0.139],[0,0],[-24.498,0],[-2.765,0.308]],"o":[[-0.03,-0.124],[0,0],[-6.875,-51.899],[0,-30.753],[-31.711,2.209],[0,0],[0,0],[0.017,0.124],[0,0],[2.734,14.936],[2.904,0],[-15.137,-2.302]],"v":[[-2.712,140.391],[-2.773,140.005],[-2.773,139.96],[-8.427,2.594],[16.905,-166.929],[-24.816,2.594],[-18.962,139.96],[-18.962,140.005],[-18.9,140.391],[-18.884,140.391],[16.905,166.93],[25.416,166.451]],"c":true},"ix":2},"nm":"Path 1","mn":"ADBE Vector Shape - Group","hd":false},{"ty":"fl","c":{"a":0,"k":[1,1,1,1],"ix":4},"o":{"a":0,"k":100,"ix":5},"r":1,"bm":0,"nm":"Fill 1","mn":"ADBE Vector Graphic - Fill","hd":false},{"ty":"tr","p":{"a":0,"k":[65.701,180.227],"ix":2},"a":{"a":0,"k":[0,0],"ix":1},"s":{"a":0,"k":[100,100],"ix":3},"r":{"a":0,"k":0,"ix":6},"o":{"a":0,"k":50,"ix":7},"sk":{"a":0,"k":0,"ix":4},"sa":{"a":0,"k":0,"ix":5},"nm":"Transform"}],"nm":"Group 4","np":4,"cix":2,"bm":0,"ix":4,"mn":"ADBE Vector Group","hd":false},{"ty":"gr","it":[{"ind":0,"ty":"sh","ix":1,"ks":{"a":0,"k":{"i":[[36.639,29.967],[4.633,-15.539],[-8.527,-38.167]],"o":[[0,0],[0,0],[-0.017,0]],"v":[[-16.126,-43.853],[-20.513,3.199],[5.469,43.853]],"c":true},"ix":2},"nm":"Path 1","mn":"ADBE Vector Shape - Group","hd":false},{"ty":"st","c":{"a":0,"k":[0.136999990426,0.122000002394,0.125,1],"ix":3},"o":{"a":0,"k":100,"ix":4},"w":{"a":0,"k":1,"ix":5},"lc":2,"lj":2,"bm":0,"nm":"Stroke 1","mn":"ADBE Vector Graphic - Stroke","hd":false},{"ty":"tr","p":{"a":0,"k":[135.046,334.504],"ix":2},"a":{"a":0,"k":[0,0],"ix":1},"s":{"a":0,"k":[100,100],"ix":3},"r":{"a":0,"k":0,"ix":6},"o":{"a":0,"k":100,"ix":7},"sk":{"a":0,"k":0,"ix":4},"sa":{"a":0,"k":0,"ix":5},"nm":"Transform"}],"nm":"Group 5","np":2,"cix":2,"bm":0,"ix":5,"mn":"ADBE Vector Group","hd":false},{"ty":"gr","it":[{"ind":0,"ty":"sh","ix":1,"ks":{"a":0,"k":{"i":[[36.639,29.967],[4.633,-15.539],[-8.527,-38.167]],"o":[[0,0],[0,0],[-0.017,0]],"v":[[-16.126,-43.853],[-20.513,3.199],[5.469,43.853]],"c":true},"ix":2},"nm":"Path 1","mn":"ADBE Vector Shape - Group","hd":false},{"ty":"fl","c":{"a":0,"k":[0.995999983245,0.902000038297,0.016000001571,1],"ix":4},"o":{"a":0,"k":100,"ix":5},"r":1,"bm":0,"nm":"Fill 1","mn":"ADBE Vector Graphic - Fill","hd":false},{"ty":"tr","p":{"a":0,"k":[135.046,334.504],"ix":2},"a":{"a":0,"k":[0,0],"ix":1},"s":{"a":0,"k":[100,100],"ix":3},"r":{"a":0,"k":0,"ix":6},"o":{"a":0,"k":100,"ix":7},"sk":{"a":0,"k":0,"ix":4},"sa":{"a":0,"k":0,"ix":5},"nm":"Transform"}],"nm":"Group 6","np":4,"cix":2,"bm":0,"ix":6,"mn":"ADBE Vector Group","hd":false},{"ty":"gr","it":[{"ind":0,"ty":"sh","ix":1,"ks":{"a":0,"k":{"i":[[36.654,29.982],[0,0],[4.001,-13.407],[-8.695,-36.083],[0,0]],"o":[[0,0],[-0.03,6.688],[0,0],[0,0],[0,0.015]],"v":[[-16.133,-44.517],[-18.807,-43.173],[-20.521,2.534],[2.789,44.517],[5.461,43.173]],"c":true},"ix":2},"nm":"Path 1","mn":"ADBE Vector Shape - Group","hd":false},{"ty":"st","c":{"a":0,"k":[0.136999990426,0.122000002394,0.125,1],"ix":3},"o":{"a":0,"k":100,"ix":4},"w":{"a":0,"k":1,"ix":5},"lc":2,"lj":2,"bm":0,"nm":"Stroke 1","mn":"ADBE Vector Graphic - Stroke","hd":false},{"ty":"tr","p":{"a":0,"k":[137.726,333.824],"ix":2},"a":{"a":0,"k":[0,0],"ix":1},"s":{"a":0,"k":[100,100],"ix":3},"r":{"a":0,"k":0,"ix":6},"o":{"a":0,"k":100,"ix":7},"sk":{"a":0,"k":0,"ix":4},"sa":{"a":0,"k":0,"ix":5},"nm":"Transform"}],"nm":"Group 7","np":2,"cix":2,"bm":0,"ix":7,"mn":"ADBE Vector Group","hd":false},{"ty":"gr","it":[{"ind":0,"ty":"sh","ix":1,"ks":{"a":0,"k":{"i":[[36.654,29.982],[0,0],[4.001,-13.407],[-8.695,-36.083],[0,0]],"o":[[0,0],[-0.03,6.688],[0,0],[0,0],[0,0.015]],"v":[[-16.133,-44.517],[-18.807,-43.173],[-20.521,2.534],[2.789,44.517],[5.461,43.173]],"c":true},"ix":2},"nm":"Path 1","mn":"ADBE Vector Shape - Group","hd":false},{"ty":"fl","c":{"a":0,"k":[0.616000007181,0.569000004787,0.093999997307,1],"ix":4},"o":{"a":0,"k":100,"ix":5},"r":1,"bm":0,"nm":"Fill 1","mn":"ADBE Vector Graphic - Fill","hd":false},{"ty":"tr","p":{"a":0,"k":[137.726,333.824],"ix":2},"a":{"a":0,"k":[0,0],"ix":1},"s":{"a":0,"k":[100,100],"ix":3},"r":{"a":0,"k":0,"ix":6},"o":{"a":0,"k":100,"ix":7},"sk":{"a":0,"k":0,"ix":4},"sa":{"a":0,"k":0,"ix":5},"nm":"Transform"}],"nm":"Group 8","np":4,"cix":2,"bm":0,"ix":8,"mn":"ADBE Vector Group","hd":false},{"ty":"gr","it":[{"ind":0,"ty":"sh","ix":1,"ks":{"a":0,"k":{"i":[[-36.653,29.967],[-4.634,-15.539],[8.527,-38.167]],"o":[[0,0],[0,0],[0,0]],"v":[[16.133,-43.853],[20.52,3.199],[-5.46,43.853]],"c":true},"ix":2},"nm":"Path 1","mn":"ADBE Vector Shape - Group","hd":false},{"ty":"st","c":{"a":0,"k":[0.136999990426,0.122000002394,0.125,1],"ix":3},"o":{"a":0,"k":100,"ix":4},"w":{"a":0,"k":1,"ix":5},"lc":2,"lj":2,"bm":0,"nm":"Stroke 1","mn":"ADBE Vector Graphic - Stroke","hd":false},{"ty":"tr","p":{"a":0,"k":[25.71,334.504],"ix":2},"a":{"a":0,"k":[0,0],"ix":1},"s":{"a":0,"k":[100,100],"ix":3},"r":{"a":0,"k":0,"ix":6},"o":{"a":0,"k":100,"ix":7},"sk":{"a":0,"k":0,"ix":4},"sa":{"a":0,"k":0,"ix":5},"nm":"Transform"}],"nm":"Group 9","np":2,"cix":2,"bm":0,"ix":9,"mn":"ADBE Vector Group","hd":false},{"ty":"gr","it":[{"ind":0,"ty":"sh","ix":1,"ks":{"a":0,"k":{"i":[[-36.653,29.967],[-4.634,-15.539],[8.527,-38.167]],"o":[[0,0],[0,0],[0,0]],"v":[[16.133,-43.853],[20.52,3.199],[-5.46,43.853]],"c":true},"ix":2},"nm":"Path 1","mn":"ADBE Vector Shape - Group","hd":false},{"ty":"fl","c":{"a":0,"k":[0.616000007181,0.569000004787,0.093999997307,1],"ix":4},"o":{"a":0,"k":100,"ix":5},"r":1,"bm":0,"nm":"Fill 1","mn":"ADBE Vector Graphic - Fill","hd":false},{"ty":"tr","p":{"a":0,"k":[25.71,334.504],"ix":2},"a":{"a":0,"k":[0,0],"ix":1},"s":{"a":0,"k":[100,100],"ix":3},"r":{"a":0,"k":0,"ix":6},"o":{"a":0,"k":100,"ix":7},"sk":{"a":0,"k":0,"ix":4},"sa":{"a":0,"k":0,"ix":5},"nm":"Transform"}],"nm":"Group 10","np":4,"cix":2,"bm":0,"ix":10,"mn":"ADBE Vector Group","hd":false},{"ty":"gr","it":[{"ind":0,"ty":"sh","ix":1,"ks":{"a":0,"k":{"i":[[-36.655,29.982],[0,0],[-4.001,-13.407],[8.695,-36.083],[0,0]],"o":[[0,0],[0.031,6.688],[0,0],[0,0],[0.016,0.015]],"v":[[16.134,-44.517],[18.807,-43.173],[20.521,2.534],[-2.787,44.517],[-5.46,43.173]],"c":true},"ix":2},"nm":"Path 1","mn":"ADBE Vector Shape - Group","hd":false},{"ty":"st","c":{"a":0,"k":[0.136999990426,0.122000002394,0.125,1],"ix":3},"o":{"a":0,"k":100,"ix":4},"w":{"a":0,"k":1,"ix":5},"lc":2,"lj":2,"bm":0,"nm":"Stroke 1","mn":"ADBE Vector Graphic - Stroke","hd":false},{"ty":"tr","p":{"a":0,"k":[23.021,333.824],"ix":2},"a":{"a":0,"k":[0,0],"ix":1},"s":{"a":0,"k":[100,100],"ix":3},"r":{"a":0,"k":0,"ix":6},"o":{"a":0,"k":100,"ix":7},"sk":{"a":0,"k":0,"ix":4},"sa":{"a":0,"k":0,"ix":5},"nm":"Transform"}],"nm":"Group 11","np":2,"cix":2,"bm":0,"ix":11,"mn":"ADBE Vector Group","hd":false},{"ty":"gr","it":[{"ind":0,"ty":"sh","ix":1,"ks":{"a":0,"k":{"i":[[-36.655,29.982],[0,0],[-4.001,-13.407],[8.695,-36.083],[0,0]],"o":[[0,0],[0.031,6.688],[0,0],[0,0],[0.016,0.015]],"v":[[16.134,-44.517],[18.807,-43.173],[20.521,2.534],[-2.787,44.517],[-5.46,43.173]],"c":true},"ix":2},"nm":"Path 1","mn":"ADBE Vector Shape - Group","hd":false},{"ty":"fl","c":{"a":0,"k":[0.995999983245,0.902000038297,0.016000001571,1],"ix":4},"o":{"a":0,"k":100,"ix":5},"r":1,"bm":0,"nm":"Fill 1","mn":"ADBE Vector Graphic - Fill","hd":false},{"ty":"tr","p":{"a":0,"k":[23.021,333.824],"ix":2},"a":{"a":0,"k":[0,0],"ix":1},"s":{"a":0,"k":[100,100],"ix":3},"r":{"a":0,"k":0,"ix":6},"o":{"a":0,"k":100,"ix":7},"sk":{"a":0,"k":0,"ix":4},"sa":{"a":0,"k":0,"ix":5},"nm":"Transform"}],"nm":"Group 12","np":4,"cix":2,"bm":0,"ix":12,"mn":"ADBE Vector Group","hd":false},{"ty":"gr","it":[{"ind":0,"ty":"sh","ix":1,"ks":{"a":0,"k":{"i":[[-5.021,9.195],[4.642,2.535],[5.021,-9.194],[-4.643,-2.535]],"o":[[5.021,-9.194],[-4.642,-2.534],[-5.021,9.196],[4.642,2.535]],"v":[[8.407,4.59],[9.092,-16.649],[-8.405,-4.591],[-9.09,16.648]],"c":true},"ix":2},"nm":"Path 1","mn":"ADBE Vector Shape - Group","hd":false},{"ty":"st","c":{"a":0,"k":[0.136999990426,0.122000002394,0.125,1],"ix":3},"o":{"a":0,"k":100,"ix":4},"w":{"a":0,"k":1,"ix":5},"lc":1,"lj":1,"ml":10,"bm":0,"nm":"Stroke 1","mn":"ADBE Vector Graphic - Stroke","hd":false},{"ty":"tr","p":{"a":0,"k":[125.281,255.113],"ix":2},"a":{"a":0,"k":[0,0],"ix":1},"s":{"a":0,"k":[100,100],"ix":3},"r":{"a":0,"k":0,"ix":6},"o":{"a":0,"k":100,"ix":7},"sk":{"a":0,"k":0,"ix":4},"sa":{"a":0,"k":0,"ix":5},"nm":"Transform"}],"nm":"Group 13","np":2,"cix":2,"bm":0,"ix":13,"mn":"ADBE Vector Group","hd":false},{"ty":"gr","it":[{"ind":0,"ty":"sh","ix":1,"ks":{"a":0,"k":{"i":[[-5.021,9.195],[4.642,2.535],[5.021,-9.194],[-4.643,-2.535]],"o":[[5.021,-9.194],[-4.642,-2.534],[-5.021,9.196],[4.642,2.535]],"v":[[8.407,4.59],[9.092,-16.649],[-8.405,-4.591],[-9.09,16.648]],"c":true},"ix":2},"nm":"Path 1","mn":"ADBE Vector Shape - Group","hd":false},{"ty":"fl","c":{"a":0,"k":[0.995999983245,0.882000014361,0.875,1],"ix":4},"o":{"a":0,"k":100,"ix":5},"r":1,"bm":0,"nm":"Fill 1","mn":"ADBE Vector Graphic - Fill","hd":false},{"ty":"tr","p":{"a":0,"k":[125.281,255.113],"ix":2},"a":{"a":0,"k":[0,0],"ix":1},"s":{"a":0,"k":[100,100],"ix":3},"r":{"a":0,"k":0,"ix":6},"o":{"a":0,"k":100,"ix":7},"sk":{"a":0,"k":0,"ix":4},"sa":{"a":0,"k":0,"ix":5},"nm":"Transform"}],"nm":"Group 14","np":4,"cix":2,"bm":0,"ix":14,"mn":"ADBE Vector Group","hd":false},{"ty":"gr","it":[{"ind":0,"ty":"sh","ix":1,"ks":{"a":0,"k":{"i":[[-6.566,12.025],[7.179,3.921],[6.568,-12.025],[-7.18,-3.921]],"o":[[6.567,-12.024],[-7.181,-3.92],[-6.565,12.026],[7.18,3.922]],"v":[[13.001,7.099],[11.89,-21.774],[-13.003,-7.101],[-11.891,21.772]],"c":true},"ix":2},"nm":"Path 1","mn":"ADBE Vector Shape - Group","hd":false},{"ty":"st","c":{"a":0,"k":[0.136999990426,0.122000002394,0.125,1],"ix":3},"o":{"a":0,"k":100,"ix":4},"w":{"a":0,"k":1,"ix":5},"lc":2,"lj":2,"bm":0,"nm":"Stroke 1","mn":"ADBE Vector Graphic - Stroke","hd":false},{"ty":"tr","p":{"a":0,"k":[125.194,255.069],"ix":2},"a":{"a":0,"k":[0,0],"ix":1},"s":{"a":0,"k":[100,100],"ix":3},"r":{"a":0,"k":0,"ix":6},"o":{"a":0,"k":100,"ix":7},"sk":{"a":0,"k":0,"ix":4},"sa":{"a":0,"k":0,"ix":5},"nm":"Transform"}],"nm":"Group 15","np":2,"cix":2,"bm":0,"ix":15,"mn":"ADBE Vector Group","hd":false},{"ty":"gr","it":[{"ind":0,"ty":"sh","ix":1,"ks":{"a":0,"k":{"i":[[-6.566,12.025],[7.179,3.921],[6.568,-12.025],[-7.18,-3.921]],"o":[[6.567,-12.024],[-7.181,-3.92],[-6.565,12.026],[7.18,3.922]],"v":[[13.001,7.099],[11.89,-21.774],[-13.003,-7.101],[-11.891,21.772]],"c":true},"ix":2},"nm":"Path 1","mn":"ADBE Vector Shape - Group","hd":false},{"ty":"fl","c":{"a":0,"k":[0.616000007181,0.569000004787,0.093999997307,1],"ix":4},"o":{"a":0,"k":100,"ix":5},"r":1,"bm":0,"nm":"Fill 1","mn":"ADBE Vector Graphic - Fill","hd":false},{"ty":"tr","p":{"a":0,"k":[125.194,255.069],"ix":2},"a":{"a":0,"k":[0,0],"ix":1},"s":{"a":0,"k":[100,100],"ix":3},"r":{"a":0,"k":0,"ix":6},"o":{"a":0,"k":100,"ix":7},"sk":{"a":0,"k":0,"ix":4},"sa":{"a":0,"k":0,"ix":5},"nm":"Transform"}],"nm":"Group 16","np":4,"cix":2,"bm":0,"ix":16,"mn":"ADBE Vector Group","hd":false},{"ty":"gr","it":[{"ind":0,"ty":"sh","ix":1,"ks":{"a":0,"k":{"i":[[0,0],[0,0],[6.566,-12.032],[-6.193,-4.542],[0,0],[0,0],[-0.279,-0.155],[-0.248,-0.11],[0,0],[0,0],[-3.538,6.487],[0.509,5.468]],"o":[[0,0],[-7.182,-3.922],[-6.239,11.431],[0,0],[0,0],[0.262,0.185],[0.232,0.124],[0,0],[0,0],[4.866,-2.516],[3.538,-6.489],[0,0]],"v":[[19.872,-17.471],[11.268,-22.166],[-13.633,-7.492],[-13.525,20.714],[-13.539,20.729],[-13.323,20.853],[-12.534,21.378],[-11.809,21.703],[-3.932,26.089],[-0.935,20.604],[12.349,6.719],[16.844,-11.971]],"c":true},"ix":2},"nm":"Path 1","mn":"ADBE Vector Shape - Group","hd":false},{"ty":"st","c":{"a":0,"k":[0.136999990426,0.122000002394,0.125,1],"ix":3},"o":{"a":0,"k":100,"ix":4},"w":{"a":0,"k":1,"ix":5},"lc":1,"lj":1,"ml":10,"bm":0,"nm":"Stroke 1","mn":"ADBE Vector Graphic - Stroke","hd":false},{"ty":"tr","p":{"a":0,"k":[117.199,250.77],"ix":2},"a":{"a":0,"k":[0,0],"ix":1},"s":{"a":0,"k":[100,100],"ix":3},"r":{"a":0,"k":0,"ix":6},"o":{"a":0,"k":100,"ix":7},"sk":{"a":0,"k":0,"ix":4},"sa":{"a":0,"k":0,"ix":5},"nm":"Transform"}],"nm":"Group 17","np":2,"cix":2,"bm":0,"ix":17,"mn":"ADBE Vector Group","hd":false},{"ty":"gr","it":[{"ind":0,"ty":"sh","ix":1,"ks":{"a":0,"k":{"i":[[0,0],[0,0],[6.566,-12.032],[-6.193,-4.542],[0,0],[0,0],[-0.279,-0.155],[-0.248,-0.11],[0,0],[0,0],[-3.538,6.487],[0.509,5.468]],"o":[[0,0],[-7.182,-3.922],[-6.239,11.431],[0,0],[0,0],[0.262,0.185],[0.232,0.124],[0,0],[0,0],[4.866,-2.516],[3.538,-6.489],[0,0]],"v":[[19.872,-17.471],[11.268,-22.166],[-13.633,-7.492],[-13.525,20.714],[-13.539,20.729],[-13.323,20.853],[-12.534,21.378],[-11.809,21.703],[-3.932,26.089],[-0.935,20.604],[12.349,6.719],[16.844,-11.971]],"c":true},"ix":2},"nm":"Path 1","mn":"ADBE Vector Shape - Group","hd":false},{"ty":"fl","c":{"a":0,"k":[0.995999983245,0.902000038297,0.016000001571,1],"ix":4},"o":{"a":0,"k":100,"ix":5},"r":1,"bm":0,"nm":"Fill 1","mn":"ADBE Vector Graphic - Fill","hd":false},{"ty":"tr","p":{"a":0,"k":[117.199,250.77],"ix":2},"a":{"a":0,"k":[0,0],"ix":1},"s":{"a":0,"k":[100,100],"ix":3},"r":{"a":0,"k":0,"ix":6},"o":{"a":0,"k":100,"ix":7},"sk":{"a":0,"k":0,"ix":4},"sa":{"a":0,"k":0,"ix":5},"nm":"Transform"}],"nm":"Group 18","np":4,"cix":2,"bm":0,"ix":18,"mn":"ADBE Vector Group","hd":false},{"ty":"gr","it":[{"ind":0,"ty":"sh","ix":1,"ks":{"a":0,"k":{"i":[[32.932,-2.286],[0,-31.819],[-33.085,0],[0,20.482]],"o":[[-32.823,2.286],[0,20.498],[33.087,0],[0,-26.12]],"v":[[-0.001,-105.808],[-59.917,70.991],[-0.001,108.093],[59.917,70.991]],"c":true},"ix":2},"nm":"Path 1","mn":"ADBE Vector Shape - Group","hd":false},{"ty":"st","c":{"a":0,"k":[0.136999990426,0.122000002394,0.125,1],"ix":3},"o":{"a":0,"k":100,"ix":4},"w":{"a":0,"k":1,"ix":5},"lc":1,"lj":1,"ml":10,"bm":0,"nm":"Stroke 1","mn":"ADBE Vector Graphic - Stroke","hd":false},{"ty":"tr","p":{"a":0,"k":[81,110.594],"ix":2},"a":{"a":0,"k":[0,0],"ix":1},"s":{"a":0,"k":[100,100],"ix":3},"r":{"a":0,"k":0,"ix":6},"o":{"a":0,"k":100,"ix":7},"sk":{"a":0,"k":0,"ix":4},"sa":{"a":0,"k":0,"ix":5},"nm":"Transform"}],"nm":"Group 19","np":2,"cix":2,"bm":0,"ix":19,"mn":"ADBE Vector Group","hd":false},{"ty":"gr","it":[{"ind":0,"ty":"sh","ix":1,"ks":{"a":0,"k":{"i":[[32.932,-2.286],[0,-31.819],[-33.085,0],[0,20.482]],"o":[[-32.823,2.286],[0,20.498],[33.087,0],[0,-26.12]],"v":[[-0.001,-105.808],[-59.917,70.991],[-0.001,108.093],[59.917,70.991]],"c":true},"ix":2},"nm":"Path 1","mn":"ADBE Vector Shape - Group","hd":false},{"ty":"fl","c":{"a":0,"k":[0.995999983245,0.902000038297,0.016000001571,1],"ix":4},"o":{"a":0,"k":100,"ix":5},"r":1,"bm":0,"nm":"Fill 1","mn":"ADBE Vector Graphic - Fill","hd":false},{"ty":"tr","p":{"a":0,"k":[81,110.594],"ix":2},"a":{"a":0,"k":[0,0],"ix":1},"s":{"a":0,"k":[100,100],"ix":3},"r":{"a":0,"k":0,"ix":6},"o":{"a":0,"k":100,"ix":7},"sk":{"a":0,"k":0,"ix":4},"sa":{"a":0,"k":0,"ix":5},"nm":"Transform"}],"nm":"Group 20","np":4,"cix":2,"bm":0,"ix":20,"mn":"ADBE Vector Group","hd":false},{"ty":"gr","it":[{"ind":0,"ty":"sh","ix":1,"ks":{"a":0,"k":{"i":[[0,0],[0,0],[-0.308,-9.87],[-27.248,0],[-7.243,15.446],[0,0]],"o":[[0,0],[0,0],[7.275,15.416],[27.279,0],[0.295,-9.854],[0,0]],"v":[[0.008,-20.002],[-57.885,-21.315],[-57.499,-5.375],[0.008,21.316],[57.529,-5.421],[57.885,-21.315]],"c":true},"ix":2},"nm":"Path 1","mn":"ADBE Vector Shape - Group","hd":false},{"ty":"fl","c":{"a":0,"k":[0.626999978458,0.583999992819,0.063000002094,1],"ix":4},"o":{"a":0,"k":100,"ix":5},"r":1,"bm":0,"nm":"Fill 1","mn":"ADBE Vector Graphic - Fill","hd":false},{"ty":"tr","p":{"a":0,"k":[80.993,206.16],"ix":2},"a":{"a":0,"k":[0,0],"ix":1},"s":{"a":0,"k":[100,100],"ix":3},"r":{"a":0,"k":0,"ix":6},"o":{"a":0,"k":100,"ix":7},"sk":{"a":0,"k":0,"ix":4},"sa":{"a":0,"k":0,"ix":5},"nm":"Transform"}],"nm":"Group 21","np":4,"cix":2,"bm":0,"ix":21,"mn":"ADBE Vector Group","hd":false},{"ty":"gr","it":[{"ind":0,"ty":"sh","ix":1,"ks":{"a":0,"k":{"i":[[-4.01,13.1],[7.822,2.393],[4.01,-13.1],[-7.822,-2.395]],"o":[[4.011,-13.1],[-7.823,-2.395],[-4.01,13.102],[7.824,2.394]],"v":[[14.165,4.335],[7.262,-23.72],[-14.163,-4.337],[-7.262,23.72]],"c":true},"ix":2},"nm":"Path 1","mn":"ADBE Vector Shape - Group","hd":false},{"ty":"fl","c":{"a":0,"k":[0.626999978458,0.583999992819,0.063000002094,1],"ix":4},"o":{"a":0,"k":100,"ix":5},"r":1,"bm":0,"nm":"Fill 1","mn":"ADBE Vector Graphic - Fill","hd":false},{"ty":"tr","p":{"a":0,"k":[113.304,259.415],"ix":2},"a":{"a":0,"k":[0,0],"ix":1},"s":{"a":0,"k":[100,100],"ix":3},"r":{"a":0,"k":0,"ix":6},"o":{"a":0,"k":100,"ix":7},"sk":{"a":0,"k":0,"ix":4},"sa":{"a":0,"k":0,"ix":5},"nm":"Transform"}],"nm":"Group 22","np":4,"cix":2,"bm":0,"ix":22,"mn":"ADBE Vector Group","hd":false},{"ty":"gr","it":[{"ind":0,"ty":"sh","ix":1,"ks":{"a":0,"k":{"i":[[0,0],[0,0],[0,0],[-9.222,-51.901],[0,0],[-0.015,-0.139],[0,0],[-24.484,0],[-2.116,15.337],[0,0]],"o":[[0,0],[0,0],[0,0],[0,0],[0.016,0.122],[0,0],[2.735,14.937],[24.944,0],[0,0],[9.314,-51.869]],"v":[[57.893,-82.167],[0,-80.854],[-57.893,-82.167],[-47.482,55.199],[-47.482,55.246],[-47.42,55.631],[-47.405,55.631],[-0.014,82.167],[47.514,54.782],[47.529,54.782]],"c":true},"ix":2},"nm":"Path 1","mn":"ADBE Vector Shape - Group","hd":false},{"ty":"st","c":{"a":0,"k":[0.136999990426,0.122000002394,0.125,1],"ix":3},"o":{"a":0,"k":100,"ix":4},"w":{"a":0,"k":1,"ix":5},"lc":1,"lj":1,"ml":10,"bm":0,"nm":"Stroke 1","mn":"ADBE Vector Graphic - Stroke","hd":false},{"ty":"tr","p":{"a":0,"k":[80.983,265.002],"ix":2},"a":{"a":0,"k":[0,0],"ix":1},"s":{"a":0,"k":[100,100],"ix":3},"r":{"a":0,"k":0,"ix":6},"o":{"a":0,"k":100,"ix":7},"sk":{"a":0,"k":0,"ix":4},"sa":{"a":0,"k":0,"ix":5},"nm":"Transform"}],"nm":"Group 23","np":2,"cix":2,"bm":0,"ix":23,"mn":"ADBE Vector Group","hd":false},{"ty":"gr","it":[{"ind":0,"ty":"sh","ix":1,"ks":{"a":0,"k":{"i":[[0,0],[0,0],[0,0],[-9.222,-51.901],[0,0],[-0.015,-0.139],[0,0],[-24.484,0],[-2.116,15.337],[0,0]],"o":[[0,0],[0,0],[0,0],[0,0],[0.016,0.122],[0,0],[2.735,14.937],[24.944,0],[0,0],[9.314,-51.869]],"v":[[57.893,-82.167],[0,-80.854],[-57.893,-82.167],[-47.482,55.199],[-47.482,55.246],[-47.42,55.631],[-47.405,55.631],[-0.014,82.167],[47.514,54.782],[47.529,54.782]],"c":true},"ix":2},"nm":"Path 1","mn":"ADBE Vector Shape - Group","hd":false},{"ty":"fl","c":{"a":0,"k":[0.995999983245,0.902000038297,0.016000001571,1],"ix":4},"o":{"a":0,"k":100,"ix":5},"r":1,"bm":0,"nm":"Fill 1","mn":"ADBE Vector Graphic - Fill","hd":false},{"ty":"tr","p":{"a":0,"k":[80.983,265.002],"ix":2},"a":{"a":0,"k":[0,0],"ix":1},"s":{"a":0,"k":[100,100],"ix":3},"r":{"a":0,"k":0,"ix":6},"o":{"a":0,"k":100,"ix":7},"sk":{"a":0,"k":0,"ix":4},"sa":{"a":0,"k":0,"ix":5},"nm":"Transform"}],"nm":"Group 24","np":4,"cix":2,"bm":0,"ix":24,"mn":"ADBE Vector Group","hd":false},{"ty":"gr","it":[{"ind":0,"ty":"sh","ix":1,"ks":{"a":0,"k":{"i":[[-0.756,10.503],[1.978,-33.225],[9.917,5.328]],"o":[[0,0],[0,0],[1.158,-10.365]],"v":[[-4.912,-23.957],[5.776,23.957],[-7.755,7.647]],"c":true},"ix":2},"nm":"Path 1","mn":"ADBE Vector Shape - Group","hd":false},{"ty":"st","c":{"a":0,"k":[0,0,0,1],"ix":3},"o":{"a":0,"k":100,"ix":4},"w":{"a":0,"k":1,"ix":5},"lc":2,"lj":2,"bm":0,"nm":"Stroke 1","mn":"ADBE Vector Graphic - Stroke","hd":false},{"ty":"tr","p":{"a":0,"k":[139.619,282.327],"ix":2},"a":{"a":0,"k":[0,0],"ix":1},"s":{"a":0,"k":[100,100],"ix":3},"r":{"a":0,"k":0,"ix":6},"o":{"a":0,"k":100,"ix":7},"sk":{"a":0,"k":0,"ix":4},"sa":{"a":0,"k":0,"ix":5},"nm":"Transform"}],"nm":"Group 25","np":2,"cix":2,"bm":0,"ix":25,"mn":"ADBE Vector Group","hd":false},{"ty":"gr","it":[{"ind":0,"ty":"sh","ix":1,"ks":{"a":0,"k":{"i":[[-0.756,10.503],[1.978,-33.225],[9.917,5.328]],"o":[[0,0],[0,0],[1.158,-10.365]],"v":[[-4.912,-23.957],[5.776,23.957],[-7.755,7.647]],"c":true},"ix":2},"nm":"Path 1","mn":"ADBE Vector Shape - Group","hd":false},{"ty":"fl","c":{"a":0,"k":[0,0,0,1],"ix":4},"o":{"a":0,"k":100,"ix":5},"r":1,"bm":0,"nm":"Fill 1","mn":"ADBE Vector Graphic - Fill","hd":false},{"ty":"tr","p":{"a":0,"k":[139.619,282.327],"ix":2},"a":{"a":0,"k":[0,0],"ix":1},"s":{"a":0,"k":[100,100],"ix":3},"r":{"a":0,"k":0,"ix":6},"o":{"a":0,"k":100,"ix":7},"sk":{"a":0,"k":0,"ix":4},"sa":{"a":0,"k":0,"ix":5},"nm":"Transform"}],"nm":"Group 26","np":4,"cix":2,"bm":0,"ix":26,"mn":"ADBE Vector Group","hd":false},{"ty":"gr","it":[{"ind":0,"ty":"sh","ix":1,"ks":{"a":0,"k":{"i":[[-0.772,10.502],[1.219,-31.495],[0,0],[9.916,5.328]],"o":[[0,0],[0,0],[0,0],[1.143,-10.364]],"v":[[-6.216,-24.482],[7.84,24.482],[4.473,23.432],[-9.059,7.121]],"c":true},"ix":2},"nm":"Path 1","mn":"ADBE Vector Shape - Group","hd":false},{"ty":"st","c":{"a":0,"k":[0,0,0,1],"ix":3},"o":{"a":0,"k":100,"ix":4},"w":{"a":0,"k":1,"ix":5},"lc":2,"lj":2,"bm":0,"nm":"Stroke 1","mn":"ADBE Vector Graphic - Stroke","hd":false},{"ty":"tr","p":{"a":0,"k":[137.572,281.801],"ix":2},"a":{"a":0,"k":[0,0],"ix":1},"s":{"a":0,"k":[100,100],"ix":3},"r":{"a":0,"k":0,"ix":6},"o":{"a":0,"k":100,"ix":7},"sk":{"a":0,"k":0,"ix":4},"sa":{"a":0,"k":0,"ix":5},"nm":"Transform"}],"nm":"Group 27","np":2,"cix":2,"bm":0,"ix":27,"mn":"ADBE Vector Group","hd":false},{"ty":"gr","it":[{"ind":0,"ty":"sh","ix":1,"ks":{"a":0,"k":{"i":[[-0.772,10.502],[1.219,-31.495],[0,0],[9.916,5.328]],"o":[[0,0],[0,0],[0,0],[1.143,-10.364]],"v":[[-6.216,-24.482],[7.84,24.482],[4.473,23.432],[-9.059,7.121]],"c":true},"ix":2},"nm":"Path 1","mn":"ADBE Vector Shape - Group","hd":false},{"ty":"fl","c":{"a":0,"k":[0,0,0,1],"ix":4},"o":{"a":0,"k":100,"ix":5},"r":1,"bm":0,"nm":"Fill 1","mn":"ADBE Vector Graphic - Fill","hd":false},{"ty":"tr","p":{"a":0,"k":[137.572,281.801],"ix":2},"a":{"a":0,"k":[0,0],"ix":1},"s":{"a":0,"k":[100,100],"ix":3},"r":{"a":0,"k":0,"ix":6},"o":{"a":0,"k":100,"ix":7},"sk":{"a":0,"k":0,"ix":4},"sa":{"a":0,"k":0,"ix":5},"nm":"Transform"}],"nm":"Group 28","np":4,"cix":2,"bm":0,"ix":28,"mn":"ADBE Vector Group","hd":false},{"ty":"gr","it":[{"ind":0,"ty":"sh","ix":1,"ks":{"a":0,"k":{"i":[[0.772,10.503],[-1.977,-33.225],[-9.917,5.328]],"o":[[0,0],[0,0],[-1.143,-10.365]],"v":[[4.912,-23.957],[-5.777,23.957],[7.754,7.647]],"c":true},"ix":2},"nm":"Path 1","mn":"ADBE Vector Shape - Group","hd":false},{"ty":"st","c":{"a":0,"k":[0,0,0,1],"ix":3},"o":{"a":0,"k":100,"ix":4},"w":{"a":0,"k":1,"ix":5},"lc":2,"lj":2,"bm":0,"nm":"Stroke 1","mn":"ADBE Vector Graphic - Stroke","hd":false},{"ty":"tr","p":{"a":0,"k":[21.561,282.327],"ix":2},"a":{"a":0,"k":[0,0],"ix":1},"s":{"a":0,"k":[100,100],"ix":3},"r":{"a":0,"k":0,"ix":6},"o":{"a":0,"k":100,"ix":7},"sk":{"a":0,"k":0,"ix":4},"sa":{"a":0,"k":0,"ix":5},"nm":"Transform"}],"nm":"Group 29","np":2,"cix":2,"bm":0,"ix":29,"mn":"ADBE Vector Group","hd":false},{"ty":"gr","it":[{"ind":0,"ty":"sh","ix":1,"ks":{"a":0,"k":{"i":[[0.772,10.503],[-1.977,-33.225],[-9.917,5.328]],"o":[[0,0],[0,0],[-1.143,-10.365]],"v":[[4.912,-23.957],[-5.777,23.957],[7.754,7.647]],"c":true},"ix":2},"nm":"Path 1","mn":"ADBE Vector Shape - Group","hd":false},{"ty":"fl","c":{"a":0,"k":[0,0,0,1],"ix":4},"o":{"a":0,"k":100,"ix":5},"r":1,"bm":0,"nm":"Fill 1","mn":"ADBE Vector Graphic - Fill","hd":false},{"ty":"tr","p":{"a":0,"k":[21.561,282.327],"ix":2},"a":{"a":0,"k":[0,0],"ix":1},"s":{"a":0,"k":[100,100],"ix":3},"r":{"a":0,"k":0,"ix":6},"o":{"a":0,"k":100,"ix":7},"sk":{"a":0,"k":0,"ix":4},"sa":{"a":0,"k":0,"ix":5},"nm":"Transform"}],"nm":"Group 30","np":4,"cix":2,"bm":0,"ix":30,"mn":"ADBE Vector Group","hd":false},{"ty":"gr","it":[{"ind":0,"ty":"sh","ix":1,"ks":{"a":0,"k":{"i":[[0.772,10.502],[-1.22,-31.495],[0,0],[-9.917,5.328]],"o":[[0,0],[0,0],[0,0],[-1.143,-10.364]],"v":[[6.217,-24.482],[-7.839,24.482],[-4.472,23.432],[9.059,7.121]],"c":true},"ix":2},"nm":"Path 1","mn":"ADBE Vector Shape - Group","hd":false},{"ty":"st","c":{"a":0,"k":[0,0,0,1],"ix":3},"o":{"a":0,"k":100,"ix":4},"w":{"a":0,"k":1,"ix":5},"lc":2,"lj":2,"bm":0,"nm":"Stroke 1","mn":"ADBE Vector Graphic - Stroke","hd":false},{"ty":"tr","p":{"a":0,"k":[23.625,281.801],"ix":2},"a":{"a":0,"k":[0,0],"ix":1},"s":{"a":0,"k":[100,100],"ix":3},"r":{"a":0,"k":0,"ix":6},"o":{"a":0,"k":100,"ix":7},"sk":{"a":0,"k":0,"ix":4},"sa":{"a":0,"k":0,"ix":5},"nm":"Transform"}],"nm":"Group 31","np":2,"cix":2,"bm":0,"ix":31,"mn":"ADBE Vector Group","hd":false},{"ty":"gr","it":[{"ind":0,"ty":"sh","ix":1,"ks":{"a":0,"k":{"i":[[0.772,10.502],[-1.22,-31.495],[0,0],[-9.917,5.328]],"o":[[0,0],[0,0],[0,0],[-1.143,-10.364]],"v":[[6.217,-24.482],[-7.839,24.482],[-4.472,23.432],[9.059,7.121]],"c":true},"ix":2},"nm":"Path 1","mn":"ADBE Vector Shape - Group","hd":false},{"ty":"fl","c":{"a":0,"k":[0,0,0,1],"ix":4},"o":{"a":0,"k":100,"ix":5},"r":1,"bm":0,"nm":"Fill 1","mn":"ADBE Vector Graphic - Fill","hd":false},{"ty":"tr","p":{"a":0,"k":[23.625,281.801],"ix":2},"a":{"a":0,"k":[0,0],"ix":1},"s":{"a":0,"k":[100,100],"ix":3},"r":{"a":0,"k":0,"ix":6},"o":{"a":0,"k":100,"ix":7},"sk":{"a":0,"k":0,"ix":4},"sa":{"a":0,"k":0,"ix":5},"nm":"Transform"}],"nm":"Group 32","np":4,"cix":2,"bm":0,"ix":32,"mn":"ADBE Vector Group","hd":false},{"ty":"gr","it":[{"ind":0,"ty":"sh","ix":1,"ks":{"a":0,"k":{"i":[[0,0],[-11.136,0],[-6.179,1.838]],"o":[[8.109,4.017],[7.291,0],[0,0]],"v":[[-24.93,-3.213],[4.555,3.213],[24.93,0.341]],"c":false},"ix":2},"nm":"Path 1","mn":"ADBE Vector Shape - Group","hd":false},{"ty":"st","c":{"a":0,"k":[0,0,0,1],"ix":3},"o":{"a":0,"k":100,"ix":4},"w":{"a":0,"k":1,"ix":5},"lc":2,"lj":2,"bm":0,"nm":"Stroke 1","mn":"ADBE Vector Graphic - Stroke","hd":false},{"ty":"tr","p":{"a":0,"k":[76.427,343.957],"ix":2},"a":{"a":0,"k":[0,0],"ix":1},"s":{"a":0,"k":[100,100],"ix":3},"r":{"a":0,"k":0,"ix":6},"o":{"a":0,"k":100,"ix":7},"sk":{"a":0,"k":0,"ix":4},"sa":{"a":0,"k":0,"ix":5},"nm":"Transform"}],"nm":"Group 33","np":2,"cix":2,"bm":0,"ix":33,"mn":"ADBE Vector Group","hd":false}],"ip":0,"op":150.000006109625,"st":4.00000016292334,"bm":0},{"ddd":1,"ind":7,"ty":4,"nm":"Layer 16 Outlines","parent":16,"sr":1,"ks":{"o":{"a":0,"k":100,"ix":11},"rx":{"a":0,"k":0,"ix":8},"ry":{"a":0,"k":0,"ix":9},"rz":{"a":0,"k":0,"ix":10},"or":{"a":0,"k":[0,0,0],"ix":7},"p":{"a":0,"k":[-2.846,277.017,0],"ix":2},"a":{"a":0,"k":[41.248,17.942,0],"ix":1},"s":{"a":1,"k":[{"i":{"x":[0.833,0.833,0.833],"y":[0.903,0.925,1.201]},"o":{"x":[0.167,0.167,0.167],"y":[0.167,0.167,0.167]},"t":0,"s":[71.759,71.616,75.561]},{"i":{"x":[0.833,0.833,0.833],"y":[1.288,-0.76,0.882]},"o":{"x":[0.167,0.167,0.167],"y":[0.609,-0.769,0.059]},"t":1,"s":[65.73,72.622,77.495]},{"i":{"x":[0.833,0.833,0.833],"y":[0.869,0.963,1.009]},"o":{"x":[0.167,0.167,0.167],"y":[0.065,0.087,0.283]},"t":2,"s":[64.774,72.523,70.887]},{"i":{"x":[0.833,0.833,0.833],"y":[0.988,1.047,0.783]},"o":{"x":[0.167,0.167,0.167],"y":[0.23,-0.067,0.008]},"t":3,"s":[69.037,70.544,68.13]},{"i":{"x":[0.833,0.833,0.833],"y":[0.984,0.679,0.894]},"o":{"x":[0.167,0.167,0.167],"y":[-0.014,0.03,0.135]},"t":4,"s":[71.464,71.644,71.179]},{"i":{"x":[0.833,0.833,0.833],"y":[0.684,0.918,1.086]},"o":{"x":[0.167,0.167,0.167],"y":[-0.02,0.113,0.396]},"t":5,"s":[69.376,69.922,76.054]},{"i":{"x":[0.833,0.833,0.833],"y":[0.895,0.925,0.845]},"o":{"x":[0.167,0.167,0.167],"y":[0.113,-4.289,0.042]},"t":6,"s":[71.066,65.02,77.352]},{"i":{"x":[0.833,0.833,0.833],"y":[1.158,-7.124,0.916]},"o":{"x":[0.167,0.167,0.167],"y":[0.407,-0.758,0.181]},"t":7,"s":[75.788,65.114,74.718]},{"i":{"x":[0.833,0.833,0.833],"y":[0.849,1.301,6.814]},"o":{"x":[0.167,0.167,0.167],"y":[0.055,0.084,11.694]},"t":8,"s":[77.004,65.104,72.463]},{"i":{"x":[0.833,0.833,0.833],"y":[0.913,0.792,1.007]},"o":{"x":[0.167,0.167,0.167],"y":[0.185,0.065,0.082]},"t":9,"s":[73.488,64.212,72.446]},{"i":{"x":[0.833,0.833,0.833],"y":[-0.16,0.891,0.808]},"o":{"x":[0.167,0.167,0.167],"y":[2.197,0.139,0.006]},"t":10,"s":[70.619,68.334,73.592]},{"i":{"x":[0.833,0.833,0.833],"y":[0.809,0.903,0.931]},"o":{"x":[0.167,0.167,0.167],"y":[0.09,0.357,0.147]},"t":11,"s":[70.506,74.518,72.353]},{"i":{"x":[0.833,0.833,0.833],"y":[0.906,1.631,0.389]},"o":{"x":[0.167,0.167,0.167],"y":[0.148,0.6,-0.416]},"t":12,"s":[69.044,76.401,70.742]},{"i":{"x":[0.833,0.833,0.833],"y":[2.143,0.772,1.05]},"o":{"x":[0.167,0.167,0.167],"y":[0.745,0.074,0.097]},"t":13,"s":[67.147,76.705,71.011]},{"i":{"x":[0.833,0.833,0.833],"y":[0.813,0.921,0.74]},"o":{"x":[0.167,0.167,0.167],"y":[0.078,0.131,0.031]},"t":14,"s":[66.908,74.1,72.713]},{"i":{"x":[0.833,0.833,0.833],"y":[0.88,-0.002,0.91]},"o":{"x":[0.167,0.167,0.167],"y":[0.15,-1.473,0.123]},"t":15,"s":[70.427,69.568,69.99]},{"i":{"x":[0.833,0.833,0.833],"y":[0.946,0.992,1.558]},"o":{"x":[0.167,0.167,0.167],"y":[0.271,0.091,1.065]},"t":16,"s":[74.802,69.811,64.218]},{"i":{"x":[0.833,0.833,0.833],"y":[0.748,0.769,0.895]},"o":{"x":[0.167,0.167,0.167],"y":[-0.156,-0.009,0.073]},"t":17,"s":[76.748,72.486,63.728]},{"i":{"x":[0.833,0.833,0.833],"y":[0.844,0.908,1.14]},"o":{"x":[0.167,0.167,0.167],"y":[0.124,0.13,0.405]},"t":18,"s":[76.07,70.071,67.498]},{"i":{"x":[0.833,0.833,0.833],"y":[0.878,1.216,0.971]},"o":{"x":[0.167,0.167,0.167],"y":[0.179,0.864,0.052]},"t":19,"s":[74.697,65.792,68.474]},{"i":{"x":[0.833,0.833,0.833],"y":[1.075,0.888,0.718]},"o":{"x":[0.167,0.167,0.167],"y":[0.263,0.06,-0.045]},"t":20,"s":[73.502,65.335,65.861]},{"i":{"x":[0.833,0.833,0.833],"y":[0.968,1.33,0.955]},"o":{"x":[0.167,0.167,0.167],"y":[0.039,0.326,0.118]},"t":21,"s":[72.947,66.979,67.555]},{"i":{"x":[0.833,0.833,0.833],"y":[0.437,0.961,0.759]},"o":{"x":[0.167,0.167,0.167],"y":[-0.053,0.067,-0.098]},"t":22,"s":[74,67.543,71.589]},{"i":{"x":[0.833,0.833,0.833],"y":[0.852,0.576,0.946]},"o":{"x":[0.167,0.167,0.167],"y":[0.098,-0.072,0.127]},"t":23,"s":[73.356,64.745,69.739]},{"i":{"x":[0.833,0.833,0.833],"y":[0.949,0.858,0.791]},"o":{"x":[0.167,0.167,0.167],"y":[0.191,0.104,-0.151]},"t":24,"s":[69.653,66.244,66.233]},{"i":{"x":[0.833,0.833,0.833],"y":[0.719,0.964,1.055]},"o":{"x":[0.167,0.167,0.167],"y":[-0.128,0.201,0.139]},"t":25,"s":[66.796,72.379,67.479]},{"i":{"x":[0.833,0.833,0.833],"y":[0.878,0.767,0.84]},"o":{"x":[0.167,0.167,0.167],"y":[0.118,-0.063,0.033]},"t":26,"s":[67.921,76.708,69.36]},{"i":{"x":[0.833,0.833,0.833],"y":[0.804,0.949,1.026]},"o":{"x":[0.167,0.167,0.167],"y":[0.263,0.13,0.174]},"t":27,"s":[70.592,74.239,66.239]},{"i":{"x":[0.833,0.833,0.833],"y":[0.907,0.764,0.812]},"o":{"x":[0.167,0.167,0.167],"y":[0.145,-0.131,0.02]},"t":28,"s":[71.828,69.812,63.376]},{"i":{"x":[0.833,0.833,0.833],"y":[2.21,0.92,0.907]},"o":{"x":[0.167,0.167,0.167],"y":[0.779,0.129,0.15]},"t":29,"s":[73.499,71.533,67.125]},{"i":{"x":[0.833,0.833,0.833],"y":[0.825,1.049,1.687]},"o":{"x":[0.167,0.167,0.167],"y":[0.078,-2.3,0.801]},"t":30,"s":[73.699,74.69,71.816]},{"i":{"x":[0.833,0.833,0.833],"y":[0.985,0.126,0.851]},"o":{"x":[0.167,0.167,0.167],"y":[0.159,0.031,0.074]},"t":31,"s":[70.592,74.58,72.361]},{"i":{"x":[0.833,0.833,0.833],"y":[0.743,0.95,0.929]},"o":{"x":[0.167,0.167,0.167],"y":[-0.018,0.092,0.189]},"t":32,"s":[67.19,74.755,67.321]},{"i":{"x":[0.833,0.833,0.833],"y":[0.894,0.946,0.224]},"o":{"x":[0.167,0.167,0.167],"y":[0.123,-0.124,-0.486]},"t":33,"s":[69.975,76.416,63.346]},{"i":{"x":[0.833,0.833,0.833],"y":[1.038,0.904,0.845]},"o":{"x":[0.167,0.167,0.167],"y":[0.393,-0.155,0.093]},"t":34,"s":[75.767,75.748,63.928]},{"i":{"x":[0.833,0.833,0.833],"y":[0.854,9.276,0.908]},"o":{"x":[0.167,0.167,0.167],"y":[0.026,0.637,0.18]},"t":35,"s":[77.326,75.982,68.766]},{"i":{"x":[0.833,0.833,0.833],"y":[0.77,0.843,1.263]},"o":{"x":[0.167,0.167,0.167],"y":[0.195,0.083,0.897]},"t":36,"s":[75.051,76.017,72.945]},{"i":{"x":[0.833,0.833,0.833],"y":[0.766,0.964,0.69]},"o":{"x":[0.167,0.167,0.167],"y":[0.131,0.177,0.063]},"t":37,"s":[73.352,72.494,73.373]},{"i":{"x":[0.833,0.833,0.833],"y":[0.881,0.817,0.821]},"o":{"x":[0.167,0.167,0.167],"y":[0.129,-0.063,0.114]},"t":38,"s":[70.354,69.361,71.592]},{"i":{"x":[0.833,0.833,0.833],"y":[0.99,1.079,0.872]},"o":{"x":[0.167,0.167,0.167],"y":[0.28,0.153,0.156]},"t":39,"s":[64.936,71.143,66.744]},{"i":{"x":[0.833,0.833,0.833],"y":[0.828,0.88,0.994]},"o":{"x":[0.167,0.167,0.167],"y":[-0.011,0.041,0.238]},"t":40,"s":[62.641,73.281,61.174]},{"i":{"x":[0.833,0.833,0.833],"y":[0.905,1.109,0.782]},"o":{"x":[0.167,0.167,0.167],"y":[0.162,0.272,-0.006]},"t":41,"s":[64.667,69.108,58.169]},{"i":{"x":[0.833,0.833,0.833],"y":[0.536,0.786,0.886]},"o":{"x":[0.167,0.167,0.167],"y":[0.675,0.047,0.135]},"t":42,"s":[66.825,67.268,60.969]},{"i":{"x":[0.833,0.833,0.833],"y":[0.741,0.93,0.78]},"o":{"x":[0.167,0.167,0.167],"y":[0.102,0.136,0.311]},"t":43,"s":[67.129,71.524,65.488]},{"i":{"x":[0.833,0.833,0.833],"y":[0.879,0.408,0.793]},"o":{"x":[0.167,0.167,0.167],"y":[0.123,-0.438,0.134]},"t":44,"s":[68.517,78.202,67.138]},{"i":{"x":[0.833,0.833,0.833],"y":[1,0.838,0.832]},"o":{"x":[0.167,0.167,0.167],"y":[0.267,0.097,0.139]},"t":45,"s":[71.441,77.135,69.852]},{"i":{"x":[0.833,0.833,0.833],"y":[0.633,0.906,0.923]},"o":{"x":[0.167,0.167,0.167],"y":[0,0.171,0.166]},"t":46,"s":[72.769,70.624,73.896]},{"i":{"x":[0.833,0.833,0.833],"y":[0.827,1.316,0.222]},"o":{"x":[0.167,0.167,0.167],"y":[0.108,0.735,-0.934]},"t":47,"s":[71.443,64.448,77.99]},{"i":{"x":[0.833,0.833,0.833],"y":[0.979,0.79,0.89]},"o":{"x":[0.167,0.167,0.167],"y":[0.161,0.066,0.093]},"t":48,"s":[66.937,63.658,77.654]},{"i":{"x":[0.833,0.833,0.833],"y":[0.75,0.887,0.793]},"o":{"x":[0.167,0.167,0.167],"y":[-0.028,0.138,0.345]},"t":49,"s":[62.105,67.448,74.858]},{"i":{"x":[0.833,0.833,0.833],"y":[0.908,1.052,0.765]},"o":{"x":[0.167,0.167,0.167],"y":[0.125,0.319,0.14]},"t":50,"s":[65.71,73.214,73.966]},{"i":{"x":[0.833,0.833,0.833],"y":[1.398,0.836,0.902]},"o":{"x":[0.167,0.167,0.167],"y":[0.845,0.032,0.129]},"t":51,"s":[72.929,75.252,72.645]},{"i":{"x":[0.833,0.833,0.833],"y":[0.855,0.908,1.238]},"o":{"x":[0.167,0.167,0.167],"y":[0.069,0.169,0.568]},"t":52,"s":[73.718,71.949,70.236]},{"i":{"x":[0.833,0.833,0.833],"y":[0.866,1.046,0.916]},"o":{"x":[0.167,0.167,0.167],"y":[0.197,0.864,0.062]},"t":53,"s":[69.161,68.734,69.822]},{"i":{"x":[0.833,0.833,0.833],"y":[0.815,0.731,-7.542]},"o":{"x":[0.167,0.167,0.167],"y":[0.219,0.03,12.475]},"t":54,"s":[65.81,68.391,71.421]},{"i":{"x":[0.833,0.833,0.833],"y":[0.966,0.698,0.872]},"o":{"x":[0.167,0.167,0.167],"y":[0.152,0.121,0.084]},"t":55,"s":[63.756,68.926,71.431]},{"i":{"x":[0.833,0.833,0.833],"y":[0.679,0.862,1.362]},"o":{"x":[0.167,0.167,0.167],"y":[-0.056,0.115,0.239]},"t":56,"s":[61.249,70.114,72.522]},{"i":{"x":[0.833,0.833,0.833],"y":[0.816,1.013,0.805]},"o":{"x":[0.167,0.167,0.167],"y":[0.113,0.211,0.068]},"t":57,"s":[62.745,73.235,73.107]},{"i":{"x":[0.833,0.833,0.833],"y":[0.895,0.88,0.873]},"o":{"x":[0.167,0.167,0.167],"y":[0.153,0.011,0.145]},"t":58,"s":[67.004,75.27,69.986]},{"i":{"x":[0.833,0.833,0.833],"y":[1.096,1.167,0.86]},"o":{"x":[0.167,0.167,0.167],"y":[0.41,0.27,0.243]},"t":59,"s":[72.124,72.913,65.797]},{"i":{"x":[0.833,0.833,0.833],"y":[0.793,0.883,0.978]},"o":{"x":[0.167,0.167,0.167],"y":[0.045,0.056,0.205]},"t":60,"s":[73.431,71.863,63.616]},{"i":{"x":[0.833,0.833,0.833],"y":[0.942,1.158,0.294]},"o":{"x":[0.167,0.167,0.167],"y":[0.139,0.289,-0.03]},"t":61,"s":[70.621,75.011,62.121]},{"i":{"x":[0.833,0.833,0.833],"y":[0.524,0.856,0.835]},"o":{"x":[0.167,0.167,0.167],"y":[-0.191,0.054,0.094]},"t":62,"s":[66.44,76.29,63.218]},{"i":{"x":[0.833,0.833,0.833],"y":[0.83,0.874,0.928]},"o":{"x":[0.167,0.167,0.167],"y":[0.101,0.197,0.168]},"t":63,"s":[67.712,72.595,71.41]},{"i":{"x":[0.833,0.833,0.833],"y":[0.907,0.9,0.247]},"o":{"x":[0.167,0.167,0.167],"y":[0.163,0.246,-0.519]},"t":64,"s":[73.707,69.894,79.441]},{"i":{"x":[0.833,0.833,0.833],"y":[1.314,1.63,0.855]},"o":{"x":[0.167,0.167,0.167],"y":[0.841,0.512,0.094]},"t":65,"s":[79.954,68.509,78.329]},{"i":{"x":[0.833,0.833,0.833],"y":[0.915,0.798,0.897]},"o":{"x":[0.167,0.167,0.167],"y":[0.066,0.074,0.197]},"t":66,"s":[80.642,68.24,69.39]},{"i":{"x":[0.833,0.833,0.833],"y":[0.01,0.938,1.015]},"o":{"x":[0.167,0.167,0.167],"y":[5.536,0.142,0.434]},"t":67,"s":[77.368,70.543,62.814]},{"i":{"x":[0.833,0.833,0.833],"y":[0.372,0.567,0.752]},"o":{"x":[0.167,0.167,0.167],"y":[0.091,-0.245,0.013]},"t":68,"s":[77.318,73.83,61.25]},{"i":{"x":[0.833,0.833,0.833],"y":[0.775,0.879,0.811]},"o":{"x":[0.167,0.167,0.167],"y":[0.096,0.103,0.125]},"t":69,"s":[76.774,72.995,63.102]},{"i":{"x":[0.833,0.833,0.833],"y":[0.906,1.026,0.892]},"o":{"x":[0.167,0.167,0.167],"y":[0.132,0.265,0.149]},"t":70,"s":[73.213,69.495,66.764]},{"i":{"x":[0.833,0.833,0.833],"y":[1.334,0.806,1.072]},"o":{"x":[0.167,0.167,0.167],"y":[0.759,0.02,0.367]},"t":71,"s":[67.14,67.893,71.425]},{"i":{"x":[0.833,0.833,0.833],"y":[0.882,0.913,0.915]},"o":{"x":[0.167,0.167,0.167],"y":[0.067,0.146,0.039]},"t":72,"s":[66.391,69.986,72.795]},{"i":{"x":[0.833,0.833,0.833],"y":[1.067,1.451,2.562]},"o":{"x":[0.167,0.167,0.167],"y":[0.284,1.921,4.038]},"t":73,"s":[70.145,72.761,70.245]},{"i":{"x":[0.833,0.833,0.833],"y":[0.819,0.917,1.027]},"o":{"x":[0.167,0.167,0.167],"y":[0.037,0.07,0.079]},"t":74,"s":[71.706,72.887,70.191]},{"i":{"x":[0.833,0.833,0.833],"y":[0.826,38.047,0.934]},"o":{"x":[0.167,0.167,0.167],"y":[0.155,-12.65,0.02]},"t":75,"s":[68.894,72.08,71.252]},{"i":{"x":[0.833,0.833,0.833],"y":[0.882,0.775,0.838]},"o":{"x":[0.167,0.167,0.167],"y":[0.16,0.083,-0.318]},"t":76,"s":[65.607,72.085,69.845]},{"i":{"x":[0.833,0.833,0.833],"y":[1.039,0.896,2.051]},"o":{"x":[0.167,0.167,0.167],"y":[0.282,0.132,0.172]},"t":77,"s":[62.029,69.732,70.137]},{"i":{"x":[0.833,0.833,0.833],"y":[0.78,1.47,0.792]},"o":{"x":[0.167,0.167,0.167],"y":[0.026,0.423,0.077]},"t":78,"s":[60.532,65.727,70.412]},{"i":{"x":[0.833,0.833,0.833],"y":[0.8,0.862,0.947]},"o":{"x":[0.167,0.167,0.167],"y":[0.134,0.071,0.139]},"t":79,"s":[62.724,64.743,66.671]},{"i":{"x":[0.833,0.833,0.833],"y":[0.837,0.982,0.663]},"o":{"x":[0.167,0.167,0.167],"y":[0.143,0.211,-0.148]},"t":80,"s":[66.314,71.279,61.067]},{"i":{"x":[0.833,0.833,0.833],"y":[0.951,0.77,0.867]},"o":{"x":[0.167,0.167,0.167],"y":[0.171,-0.022,0.111]},"t":81,"s":[71.353,75.529,63.082]},{"i":{"x":[0.833,0.833,0.833],"y":[0.579,0.924,0.912]},"o":{"x":[0.167,0.167,0.167],"y":[-0.121,0.131,0.222]},"t":82,"s":[76.17,72.178,69.206]},{"i":{"x":[0.833,0.833,0.833],"y":[0.874,0.258,1.237]},"o":{"x":[0.167,0.167,0.167],"y":[0.104,-0.831,1.528]},"t":83,"s":[74.206,66.273,72.885]},{"i":{"x":[0.833,0.833,0.833],"y":[0.887,0.854,0.886]},"o":{"x":[0.167,0.167,0.167],"y":[0.245,0.094,0.062]},"t":84,"s":[66.246,66.811,73.098]},{"i":{"x":[0.833,0.833,0.833],"y":[0.866,0.93,-0.05]},"o":{"x":[0.167,0.167,0.167],"y":[0.319,0.194,0.307]},"t":85,"s":[62.141,71.065,72.281]},{"i":{"x":[0.833,0.833,0.833],"y":[1.071,0.44,0.811]},"o":{"x":[0.167,0.167,0.167],"y":[0.222,-0.439,0.091]},"t":86,"s":[60.691,74.266,71.976]},{"i":{"x":[0.833,0.833,0.833],"y":[0.769,0.794,0.872]},"o":{"x":[0.167,0.167,0.167],"y":[0.038,0.098,0.149]},"t":87,"s":[59.817,73.755,68.447]},{"i":{"x":[0.833,0.833,0.833],"y":[0.822,0.918,1.059]},"o":{"x":[0.167,0.167,0.167],"y":[0.13,0.14,0.24]},"t":88,"s":[61.437,70.83,63.987]},{"i":{"x":[0.833,0.833,0.833],"y":[0.843,-4.822,0.79]},"o":{"x":[0.167,0.167,0.167],"y":[0.157,-5.207,0.034]},"t":89,"s":[64.315,66.508,61.619]},{"i":{"x":[0.833,0.833,0.833],"y":[0.963,0.879,0.892]},"o":{"x":[0.167,0.167,0.167],"y":[0.178,0.085,0.138]},"t":90,"s":[67.569,66.576,65.653]},{"i":{"x":[0.833,0.833,0.833],"y":[0.617,0.893,0.976]},"o":{"x":[0.167,0.167,0.167],"y":[-0.065,0.265,0.362]},"t":91,"s":[70.44,71.265,71.793]},{"i":{"x":[0.833,0.833,0.833],"y":[0.872,0.543,0.892]},"o":{"x":[0.167,0.167,0.167],"y":[0.106,0.381,-0.033]},"t":92,"s":[68.826,73.411,73.626]},{"i":{"x":[0.833,0.833,0.833],"y":[0.945,0.901,0.449]},"o":{"x":[0.167,0.167,0.167],"y":[0.239,0.102,0.362]},"t":93,"s":[63.015,74.013,72.311]},{"i":{"x":[0.833,0.833,0.833],"y":[0.788,1.516,0.848]},"o":{"x":[0.167,0.167,0.167],"y":[-0.165,0.529,0.098]},"t":94,"s":[59.898,76.716,71.918]},{"i":{"x":[0.833,0.833,0.833],"y":[0.877,0.884,1.039]},"o":{"x":[0.167,0.167,0.167],"y":[0.137,0.072,0.184]},"t":95,"s":[60.945,77.221,69.713]},{"i":{"x":[0.833,0.833,0.833],"y":[0.422,0.766,0.782]},"o":{"x":[0.167,0.167,0.167],"y":[0.258,0.296,0.027]},"t":96,"s":[62.556,73.587,67.892]},{"i":{"x":[0.833,0.833,0.833],"y":[0.778,0.825,0.946]},"o":{"x":[0.167,0.167,0.167],"y":[0.097,0.129,0.135]},"t":97,"s":[63.323,72.163,70.575]},{"i":{"x":[0.833,0.833,0.833],"y":[0.873,0.969,0.681]},"o":{"x":[0.167,0.167,0.167],"y":[0.133,0.159,-0.157]},"t":98,"s":[67.875,69.59,74.922]},{"i":{"x":[0.833,0.833,0.833],"y":[0.975,0.692,0.906]},"o":{"x":[0.167,0.167,0.167],"y":[0.244,-0.049,0.113]},"t":99,"s":[75.455,66.773,73.411]},{"i":{"x":[0.833,0.833,0.833],"y":[0.71,0.938,0.844]},"o":{"x":[0.167,0.167,0.167],"y":[-0.036,0.114,0.747]},"t":100,"s":[79.395,68.551,69.14]},{"i":{"x":[0.833,0.833,0.833],"y":[0.862,0.561,0.379]},"o":{"x":[0.167,0.167,0.167],"y":[0.117,-0.237,0.178]},"t":101,"s":[76.648,73.345,68.604]},{"i":{"x":[0.833,0.833,0.833],"y":[0.928,0.897,0.869]},"o":{"x":[0.167,0.167,0.167],"y":[0.209,0.103,0.096]},"t":102,"s":[69.835,72.097,68.133]},{"i":{"x":[0.833,0.833,0.833],"y":[0.393,1.269,0.903]},"o":{"x":[0.167,0.167,0.167],"y":[-0.504,0.441,0.229]},"t":103,"s":[65.328,66.772,65.096]},{"i":{"x":[0.833,0.833,0.833],"y":[0.855,0.84,0.23]},"o":{"x":[0.167,0.167,0.167],"y":[0.097,0.064,0.574]},"t":104,"s":[65.967,65.533,63.354]},{"i":{"x":[0.833,0.833,0.833],"y":[0.932,0.925,0.808]},"o":{"x":[0.167,0.167,0.167],"y":[0.195,0.174,0.093]},"t":105,"s":[69.985,70.767,63.058]},{"i":{"x":[0.833,0.833,0.833],"y":[0.538,0.346,1.029]},"o":{"x":[0.167,0.167,0.167],"y":[-0.373,-0.749,0.147]},"t":106,"s":[72.979,75.571,60.62]},{"i":{"x":[0.833,0.833,0.833],"y":[0.863,0.867,0.777]},"o":{"x":[0.167,0.167,0.167],"y":[0.102,0.095,0.021]},"t":107,"s":[72.432,75.09,57.435]},{"i":{"x":[0.833,0.833,0.833],"y":[0.868,1.073,0.842]},"o":{"x":[0.167,0.167,0.167],"y":[0.213,0.223,0.133]},"t":108,"s":[69.949,71.795,61.724]},{"i":{"x":[0.833,0.833,0.833],"y":[0.648,0.888,0.902]},"o":{"x":[0.167,0.167,0.167],"y":[0.227,0.039,0.176]},"t":109,"s":[68.35,69.83,68.923]},{"i":{"x":[0.833,0.833,0.833],"y":[0.827,1.21,1.132]},"o":{"x":[0.167,0.167,0.167],"y":[0.109,0.324,0.547]},"t":110,"s":[67.426,73.526,75.411]},{"i":{"x":[0.833,0.833,0.833],"y":[1.006,0.789,0.85]},"o":{"x":[0.167,0.167,0.167],"y":[0.161,0.06,0.051]},"t":111,"s":[64.452,74.804,76.577]},{"i":{"x":[0.833,0.833,0.833],"y":[0.776,0.937,0.935]},"o":{"x":[0.167,0.167,0.167],"y":[0.006,0.138,0.187]},"t":112,"s":[61.268,70.311,73.561]},{"i":{"x":[0.833,0.833,0.833],"y":[0.913,0.571,0.617]},"o":{"x":[0.167,0.167,0.167],"y":[0.133,-0.267,-0.296]},"t":113,"s":[64.699,63.406,71.14]},{"i":{"x":[0.833,0.833,0.833],"y":[1.858,0.925,0.87]},"o":{"x":[0.167,0.167,0.167],"y":[2.033,0.103,0.107]},"t":114,"s":[70.486,65.051,71.672]},{"i":{"x":[0.833,0.833,0.833],"y":[0.971,0.53,0.932]},"o":{"x":[0.167,0.167,0.167],"y":[0.076,-0.707,0.232]},"t":115,"s":[70.733,71.87,73.584]},{"i":{"x":[0.833,0.833,0.833],"y":[0.741,0.973,0.608]},"o":{"x":[0.167,0.167,0.167],"y":[-0.044,0.101,-0.37]},"t":116,"s":[67.94,71.151,74.655]},{"i":{"x":[0.833,0.833,0.833],"y":[0.809,0.819,0.521]},"o":{"x":[0.167,0.167,0.167],"y":[0.123,-0.039,0.106]},"t":117,"s":[69.769,67.817,74.458]},{"i":{"x":[0.833,0.833,0.833],"y":[0.881,0.971,0.791]},"o":{"x":[0.167,0.167,0.167],"y":[0.148,0.155,0.101]},"t":118,"s":[73.616,70.079,73.73]},{"i":{"x":[0.833,0.833,0.833],"y":[0.989,0.896,0.878]},"o":{"x":[0.167,0.167,0.167],"y":[0.277,-0.044,0.139]},"t":119,"s":[78.595,72.729,70.273]},{"i":{"x":[0.833,0.833,0.833],"y":[0.814,0.904,1.015]},"o":{"x":[0.167,0.167,0.167],"y":[-0.013,0.425,0.262]},"t":120,"s":[80.732,70.998,65.077]},{"i":{"x":[0.833,0.833,0.833],"y":[0.933,1.584,0.875]},"o":{"x":[0.167,0.167,0.167],"y":[0.151,0.629,0.012]},"t":121,"s":[78.885,70.576,62.648]},{"i":{"x":[0.833,0.833,0.833],"y":[0.633,0.443,1.09]},"o":{"x":[0.167,0.167,0.167],"y":[-0.35,0.073,0.251]},"t":122,"s":[76.603,70.512,65.506]},{"i":{"x":[0.833,0.833,0.833],"y":[1.195,0.981,0.934]},"o":{"x":[0.167,0.167,0.167],"y":[0.108,0.098,0.043]},"t":123,"s":[77.043,71.028,66.925]},{"i":{"x":[0.833,0.833,0.833],"y":[0.808,0.705,0.652]},"o":{"x":[0.167,0.167,0.167],"y":[0.058,-0.025,-0.318]},"t":124,"s":[78.535,73.963,63.969]},{"i":{"x":[0.833,0.833,0.833],"y":[0.91,0.91,1.04]},"o":{"x":[0.167,0.167,0.167],"y":[0.147,0.116,0.11]},"t":125,"s":[73.545,71.704,64.583]},{"i":{"x":[0.833,0.833,0.833],"y":[1.396,1.934,0.813]},"o":{"x":[0.167,0.167,0.167],"y":[1.058,1.147,0.027]},"t":126,"s":[67.034,65.971,66.532]},{"i":{"x":[0.833,0.833,0.833],"y":[0.991,0.931,0.969]},"o":{"x":[0.167,0.167,0.167],"y":[0.069,0.077,0.15]},"t":127,"s":[66.478,65.522,63.652]},{"i":{"x":[0.833,0.833,0.833],"y":[0.732,0.33,0.808]},"o":{"x":[0.167,0.167,0.167],"y":[-0.01,-0.418,-0.049]},"t":128,"s":[69.681,71.001,60.068]},{"i":{"x":[0.833,0.833,0.833],"y":[0.914,0.904,0.895]},"o":{"x":[0.167,0.167,0.167],"y":[0.121,0.095,0.147]},"t":129,"s":[66.823,70.091,62.317]},{"i":{"x":[0.833,0.833,0.833],"y":[2.337,1.135,0.744]},"o":{"x":[0.167,0.167,0.167],"y":[3.136,0.631,0.401]},"t":130,"s":[60.493,63.683,65.241]},{"i":{"x":[0.833,0.833,0.833],"y":[0.954,0.963,0.816]},"o":{"x":[0.167,0.167,0.167],"y":[0.078,0.052,0.123]},"t":131,"s":[60.321,62.708,66.007]},{"i":{"x":[0.833,0.833,0.833],"y":[0.805,0.861,0.98]},"o":{"x":[0.167,0.167,0.167],"y":[-0.101,-0.066,0.152]},"t":132,"s":[63.265,65.265,67.596]},{"i":{"x":[0.833,0.833,0.833],"y":[1.098,1.125,0.767]},"o":{"x":[0.167,0.167,0.167],"y":[0.145,0.207,-0.027]},"t":133,"s":[61.934,63.835,69.518]},{"i":{"x":[0.833,0.833,0.833],"y":[0.839,0.922,0.93]},"o":{"x":[0.167,0.167,0.167],"y":[0.045,0.05,0.13]},"t":134,"s":[60.146,62.876,68.066]},{"i":{"x":[0.833,0.833,0.833],"y":[0.911,-1.334,0.394]},"o":{"x":[0.167,0.167,0.167],"y":[0.173,-1.13,-0.427]},"t":135,"s":[64.027,65.274,65.452]},{"i":{"x":[0.833,0.833,0.833],"y":[0.346,0.905,0.808]},"o":{"x":[0.167,0.167,0.167],"y":[1.282,0.086,0.097]},"t":136,"s":[67.628,65.11,65.88]},{"i":{"x":[0.833,0.833,0.833],"y":[0.756,1.362,0.84]},"o":{"x":[0.167,0.167,0.167],"y":[0.096,0.657,0.147]},"t":137,"s":[67.878,60.662,68.558]},{"i":{"x":[0.833,0.833,0.833],"y":[0.966,0.758,0.909]},"o":{"x":[0.167,0.167,0.167],"y":[0.127,0.068,0.174]},"t":138,"s":[69.593,60.016,72.051]},{"i":{"x":[0.833,0.833,0.833],"y":[0.691,0.871,1.257]},"o":{"x":[0.167,0.167,0.167],"y":[-0.058,0.127,1.004]},"t":139,"s":[72.893,63.469,75.258]},{"i":{"x":[0.833,0.833,0.833],"y":[0.902,0.946,0.975]},"o":{"x":[0.167,0.167,0.167],"y":[0.114,0.235,0.063]},"t":140,"s":[70.946,70.049,75.549]},{"i":{"x":[0.833,0.833,0.833],"y":[1.012,0.554,0.954]},"o":{"x":[0.167,0.167,0.167],"y":[0.568,-0.156,-0.036]},"t":141,"s":[65.665,73.675,74.363]},{"i":{"x":[0.833,0.833,0.833],"y":[0.958,0.848,0.092]},"o":{"x":[0.167,0.167,0.167],"y":[0.011,0.102,-0.104]},"t":142,"s":[64.758,72.413,75.194]},{"i":{"x":[0.833,0.833,0.833],"y":[0.942,0.916,0.864]},"o":{"x":[0.167,0.167,0.167],"y":[-0.086,0.185,0.092]},"t":143,"s":[65.797,66.916,74.825]},{"i":{"x":[0.833,0.833,0.833],"y":[-0.097,33.122,0.861]},"o":{"x":[0.167,0.167,0.167],"y":[-0.187,27.713,0.214]},"t":144,"s":[65.285,62.416,71.168]},{"i":{"x":[0.833,0.833,0.833],"y":[0.943,0.863,0.832]},"o":{"x":[0.167,0.167,0.167],"y":[0.09,0.083,0.209]},"t":145,"s":[65.443,62.402,68.842]},{"i":{"x":[0.833,0.833,0.833],"y":[0.522,0.962,0.887]},"o":{"x":[0.167,0.167,0.167],"y":[-0.178,0.212,0.165]},"t":146,"s":[67.364,67.648,67.296]},{"i":{"x":[0.833,0.833,0.833],"y":[0.814,0.722,0.543]},"o":{"x":[0.167,0.167,0.167],"y":[0.101,-0.069,0.319]},"t":147,"s":[66.75,71.041,65.724]},{"i":{"x":[0.833,0.833,0.833],"y":[0.833,0.833,0.833]},"o":{"x":[0.167,0.167,0.167],"y":[0.151,0.119,0.102]},"t":148,"s":[63.844,69.183,65.169]},{"t":149.000006068894,"s":[60.259,64.85,62.682]}],"ix":6}},"ao":0,"shapes":[{"ty":"gr","it":[{"ind":0,"ty":"sh","ix":1,"ks":{"a":0,"k":{"i":[[0,0],[0,-11.198],[0,0],[0,22.242],[-4.062,7.29]],"o":[[4.108,7.306],[0,22.242],[0,0],[0,-11.121],[0,0]],"v":[[15.771,-48.919],[22.413,-20.297],[0,48.919],[-22.413,-20.297],[-15.848,-48.779]],"c":false},"ix":2},"nm":"Path 1","mn":"ADBE Vector Shape - Group","hd":false},{"ty":"st","c":{"a":0,"k":[0,0,0,1],"ix":3},"o":{"a":0,"k":100,"ix":4},"w":{"a":0,"k":1,"ix":5},"lc":2,"lj":2,"bm":0,"nm":"Stroke 1","mn":"ADBE Vector Graphic - Stroke","hd":false},{"ty":"tr","p":{"a":0,"k":[41.232,61.561],"ix":2},"a":{"a":0,"k":[0,0],"ix":1},"s":{"a":0,"k":[100,100],"ix":3},"r":{"a":0,"k":0,"ix":6},"o":{"a":0,"k":100,"ix":7},"sk":{"a":0,"k":0,"ix":4},"sa":{"a":0,"k":0,"ix":5},"nm":"Transform"}],"nm":"Group 1","np":2,"cix":2,"bm":0,"ix":1,"mn":"ADBE Vector Group","hd":false},{"ty":"gr","it":[{"ind":0,"ty":"sh","ix":1,"ks":{"a":0,"k":{"i":[[0,0],[0,-21.841],[0,0],[22.646,-0.016]],"o":[[21.839,-0.015],[0,0],[0,-22.645],[0,0]],"v":[[0.001,-54.005],[39.54,-14.464],[40.998,-14.464],[0,-55.462]],"c":true},"ix":2},"nm":"Path 1","mn":"ADBE Vector Shape - Group","hd":false},{"ind":1,"ty":"sh","ix":2,"ks":{"a":0,"k":{"i":[[0,0],[-21.841,0],[0,0],[0,-22.645]],"o":[[0,-21.841],[0,0],[-22.645,0],[0,0]],"v":[[-39.541,-14.464],[0,-54.005],[0,-55.462],[-40.998,-14.464]],"c":true},"ix":2},"nm":"Path 2","mn":"ADBE Vector Shape - Group","hd":false},{"ind":2,"ty":"sh","ix":3,"ks":{"a":0,"k":{"i":[[-0.553,0.474],[0,0],[0,0],[0.003,0.003],[0.011,0.012],[0.038,0.046],[0.147,0.173],[0.549,0.663],[1.883,2.371],[5.021,7.244],[3.755,7.488],[0,5.381],[0,0],[-3.784,-7.549],[-5.044,-7.276],[-3.783,-4.758],[-1.104,-1.332],[-0.296,-0.35],[-0.077,-0.09],[-0.021,-0.022],[-0.005,-0.006],[-0.001,-0.001],[0,0]],"o":[[0,0],[0,0],[-0.001,-0.001],[-0.004,-0.004],[-0.019,-0.021],[-0.076,-0.088],[-0.293,-0.349],[-1.099,-1.324],[-3.769,-4.742],[-5.024,-7.248],[-3.766,-7.514],[0,0],[0,5.739],[3.797,7.575],[5.044,7.279],[1.89,2.38],[0.552,0.666],[0.147,0.176],[0.038,0.046],[0.01,0.011],[0.002,0.003],[0,0],[0,0]],"v":[[0,54.751],[0.553,54.277],[0.552,54.275],[0.546,54.268],[0.524,54.243],[0.44,54.142],[0.105,53.748],[-1.169,52.223],[-5.721,46.61],[-19.535,28.068],[-33.326,5.407],[-39.541,-14.464],[-40.998,-14.464],[-34.629,6.06],[-20.733,28.899],[-6.862,47.517],[-2.291,53.154],[-1.009,54.687],[-0.671,55.087],[-0.583,55.189],[-0.561,55.215],[-0.556,55.223],[-0.554,55.225]],"c":true},"ix":2},"nm":"Path 3","mn":"ADBE Vector Shape - Group","hd":false},{"ind":3,"ty":"sh","ix":4,"ks":{"a":0,"k":{"i":[[0,0],[3.766,-7.514],[5.022,-7.248],[3.767,-4.742],[1.1,-1.324],[0.294,-0.349],[0.074,-0.088],[0.019,-0.021],[0.006,-0.004],[0,-0.001],[0,-0.002],[0,0],[0,0],[0,0.002],[-0.003,0.003],[-0.009,0.011],[-0.038,0.046],[-0.149,0.176],[-0.551,0.666],[-1.892,2.38],[-5.046,7.279],[-3.796,7.575],[0,5.739]],"o":[[0,5.381],[-3.753,7.488],[-5.023,7.244],[-1.885,2.371],[-0.547,0.663],[-0.146,0.173],[-0.038,0.046],[-0.01,0.012],[-0.001,0.003],[-0.002,0],[0,0],[0.553,0.474],[0,0],[0.001,-0.001],[0.005,-0.006],[0.02,-0.022],[0.077,-0.09],[0.296,-0.35],[1.105,-1.332],[3.781,-4.758],[5.043,-7.276],[3.784,-7.549],[0,0]],"v":[[39.54,-14.464],[33.325,5.407],[19.536,28.068],[5.722,46.61],[1.168,52.223],[-0.105,53.748],[-0.439,54.142],[-0.525,54.243],[-0.547,54.268],[-0.551,54.275],[-0.553,54.277],[0,54.751],[0.553,55.225],[0.555,55.223],[0.561,55.215],[0.583,55.189],[0.67,55.087],[1.01,54.687],[2.291,53.154],[6.863,47.517],[20.734,28.899],[34.628,6.06],[40.998,-14.464]],"c":true},"ix":2},"nm":"Path 4","mn":"ADBE Vector Shape - Group","hd":false},{"ind":4,"ty":"sh","ix":5,"ks":{"a":0,"k":{"i":[[0,0],[0,0],[0,0]],"o":[[0,0],[0,0],[0,0]],"v":[[0,-54.733],[0,-54.005],[0.001,-54.005]],"c":true},"ix":2},"nm":"Path 5","mn":"ADBE Vector Shape - Group","hd":false},{"ind":5,"ty":"sh","ix":6,"ks":{"a":0,"k":{"i":[[0,0],[0,0],[-0.213,0],[-0.138,0.161]],"o":[[0,0],[0.138,0.161],[0.212,0],[0,0]],"v":[[0,54.751],[-0.553,55.225],[0,55.479],[0.553,55.225]],"c":true},"ix":2},"nm":"Path 6","mn":"ADBE Vector Shape - Group","hd":false},{"ty":"mm","mm":1,"nm":"Merge Paths 1","mn":"ADBE Vector Filter - Merge","hd":false},{"ty":"fl","c":{"a":0,"k":[0,0,0,1],"ix":4},"o":{"a":0,"k":100,"ix":5},"r":1,"bm":0,"nm":"Fill 1","mn":"ADBE Vector Graphic - Fill","hd":false},{"ty":"tr","p":{"a":0,"k":[41.248,55.729],"ix":2},"a":{"a":0,"k":[0,0],"ix":1},"s":{"a":0,"k":[100,100],"ix":3},"r":{"a":0,"k":0,"ix":6},"o":{"a":0,"k":100,"ix":7},"sk":{"a":0,"k":0,"ix":4},"sa":{"a":0,"k":0,"ix":5},"nm":"Transform"}],"nm":"Group 2","np":10,"cix":2,"bm":0,"ix":2,"mn":"ADBE Vector Group","hd":false},{"ty":"gr","it":[{"ind":0,"ty":"sh","ix":1,"ks":{"a":0,"k":{"i":[[0,-22.243],[0,0],[0,22.242],[-22.242,0]],"o":[[0,22.242],[0,0],[0,-22.243],[22.244,-0.014]],"v":[[40.269,-14.473],[-0.001,54.742],[-40.27,-14.473],[-0.001,-54.743]],"c":true},"ix":2},"nm":"Path 1","mn":"ADBE Vector Shape - Group","hd":false},{"ty":"fl","c":{"a":0,"k":[0.984000052658,0.313999998803,0,1],"ix":4},"o":{"a":0,"k":100,"ix":5},"r":1,"bm":0,"nm":"Fill 1","mn":"ADBE Vector Graphic - Fill","hd":false},{"ty":"tr","p":{"a":0,"k":[41.248,55.737],"ix":2},"a":{"a":0,"k":[0,0],"ix":1},"s":{"a":0,"k":[100,100],"ix":3},"r":{"a":0,"k":0,"ix":6},"o":{"a":0,"k":100,"ix":7},"sk":{"a":0,"k":0,"ix":4},"sa":{"a":0,"k":0,"ix":5},"nm":"Transform"}],"nm":"Group 3","np":4,"cix":2,"bm":0,"ix":3,"mn":"ADBE Vector Group","hd":false}],"ip":0,"op":150.000006109625,"st":4.00000016292334,"bm":0},{"ddd":0,"ind":8,"ty":4,"nm":"Layer 2 Outlines","parent":1,"sr":1,"ks":{"o":{"a":0,"k":100,"ix":11},"r":{"a":0,"k":0,"ix":10},"p":{"a":0,"k":[-61.99,264.823,0],"ix":2},"a":{"a":0,"k":[26.575,26.576,0],"ix":1},"s":{"a":1,"k":[{"i":{"x":[0.667,0.667,0.667],"y":[1,1,1]},"o":{"x":[0.333,0.333,0.333],"y":[0,0,0]},"t":-9,"s":[75,75,100]},{"i":{"x":[0.667,0.667,0.667],"y":[1,1,1]},"o":{"x":[0.333,0.333,0.333],"y":[0,0,0]},"t":11,"s":[0,0,100]},{"i":{"x":[0.667,0.667,0.667],"y":[1,1,1]},"o":{"x":[0.333,0.333,0.333],"y":[0,0,0]},"t":31,"s":[100,100,100]},{"i":{"x":[0.667,0.667,0.667],"y":[1,1,1]},"o":{"x":[0.167,0.167,0.167],"y":[0,0,0]},"t":51,"s":[0,0,100]},{"i":{"x":[0.667,0.667,0.667],"y":[1,1,1]},"o":{"x":[0.333,0.333,0.333],"y":[0,0,0]},"t":70,"s":[100,100,100]},{"t":90.0000036657751,"s":[0,0,100]}],"ix":6}},"ao":0,"shapes":[{"ty":"gr","it":[{"ind":0,"ty":"sh","ix":1,"ks":{"a":0,"k":{"i":[[-19.011,0],[0,19.013],[19.011,0],[0,-19.011]],"o":[[19.011,0],[0,-19.011],[-19.011,0],[0,19.013]],"v":[[0,34.423],[34.423,0],[0,-34.423],[-34.423,0]],"c":true},"ix":2},"nm":"Path 1","mn":"ADBE Vector Shape - Group","hd":false},{"ty":"st","c":{"a":0,"k":[0,0,0,1],"ix":3},"o":{"a":0,"k":100,"ix":4},"w":{"a":0,"k":0.7,"ix":5},"lc":2,"lj":2,"bm":0,"nm":"Stroke 1","mn":"ADBE Vector Graphic - Stroke","hd":false},{"ty":"fl","c":{"a":0,"k":[1,1,1,1],"ix":4},"o":{"a":0,"k":100,"ix":5},"r":1,"bm":0,"nm":"Fill 1","mn":"ADBE Vector Graphic - Fill","hd":false},{"ty":"tr","p":{"a":0,"k":[36.173,36.173],"ix":2},"a":{"a":0,"k":[0,0],"ix":1},"s":{"a":0,"k":[100,100],"ix":3},"r":{"a":0,"k":0,"ix":6},"o":{"a":0,"k":100,"ix":7},"sk":{"a":0,"k":0,"ix":4},"sa":{"a":0,"k":0,"ix":5},"nm":"Transform"}],"nm":"Group 1","np":3,"cix":2,"bm":0,"ix":1,"mn":"ADBE Vector Group","hd":false}],"ip":0,"op":150.000006109625,"st":0,"bm":0},{"ddd":0,"ind":9,"ty":4,"nm":"Layer 3 Outlines","parent":1,"sr":1,"ks":{"o":{"a":0,"k":100,"ix":11},"r":{"a":0,"k":0,"ix":10},"p":{"a":0,"k":[34.51,281.323,0],"ix":2},"a":{"a":0,"k":[26.575,26.576,0],"ix":1},"s":{"a":1,"k":[{"i":{"x":[0.667,0.667,0.667],"y":[1,1,1]},"o":{"x":[0.333,0.333,0.333],"y":[0,0,0]},"t":5,"s":[100,100,100]},{"i":{"x":[0.667,0.667,0.667],"y":[1,1,1]},"o":{"x":[0.333,0.333,0.333],"y":[0,0,0]},"t":23,"s":[0,0,100]},{"i":{"x":[0.667,0.667,0.667],"y":[1,1,1]},"o":{"x":[0.333,0.333,0.333],"y":[0,0,0]},"t":41,"s":[100,100,100]},{"i":{"x":[0.667,0.667,0.667],"y":[1,1,1]},"o":{"x":[0.167,0.167,0.167],"y":[0,0,0]},"t":61,"s":[0,0,100]},{"t":82.0000033399285,"s":[100,100,100]}],"ix":6}},"ao":0,"shapes":[{"ty":"gr","it":[{"ind":0,"ty":"sh","ix":1,"ks":{"a":0,"k":{"i":[[-13.711,0],[0,13.711],[13.711,0],[0,-13.711]],"o":[[13.711,0],[0,-13.711],[-13.711,0],[0,13.711]],"v":[[0,24.826],[24.826,-0.001],[0,-24.826],[-24.826,-0.001]],"c":true},"ix":2},"nm":"Path 1","mn":"ADBE Vector Shape - Group","hd":false},{"ty":"st","c":{"a":0,"k":[0,0,0,1],"ix":3},"o":{"a":0,"k":100,"ix":4},"w":{"a":0,"k":0.7,"ix":5},"lc":2,"lj":2,"bm":0,"nm":"Stroke 1","mn":"ADBE Vector Graphic - Stroke","hd":false},{"ty":"fl","c":{"a":0,"k":[1,1,1,1],"ix":4},"o":{"a":0,"k":100,"ix":5},"r":1,"bm":0,"nm":"Fill 1","mn":"ADBE Vector Graphic - Fill","hd":false},{"ty":"tr","p":{"a":0,"k":[26.575,26.576],"ix":2},"a":{"a":0,"k":[0,0],"ix":1},"s":{"a":0,"k":[100,100],"ix":3},"r":{"a":0,"k":0,"ix":6},"o":{"a":0,"k":100,"ix":7},"sk":{"a":0,"k":0,"ix":4},"sa":{"a":0,"k":0,"ix":5},"nm":"Transform"}],"nm":"Group 1","np":3,"cix":2,"bm":0,"ix":1,"mn":"ADBE Vector Group","hd":false}],"ip":0,"op":150.000006109625,"st":0,"bm":0},{"ddd":0,"ind":10,"ty":4,"nm":"Layer 4 Outlines","parent":1,"sr":1,"ks":{"o":{"a":0,"k":100,"ix":11},"r":{"a":0,"k":0,"ix":10},"p":{"a":0,"k":[43.452,241.768,0],"ix":2},"a":{"a":0,"k":[14.653,14.654,0],"ix":1},"s":{"a":1,"k":[{"i":{"x":[0.667,0.667,0.667],"y":[1,1,1]},"o":{"x":[0.333,0.333,0.333],"y":[0,0,0]},"t":5,"s":[0,0,100]},{"i":{"x":[0.667,0.667,0.667],"y":[1,1,1]},"o":{"x":[0.333,0.333,0.333],"y":[0,0,0]},"t":15,"s":[75,75,100]},{"i":{"x":[0.667,0.667,0.667],"y":[1,1,1]},"o":{"x":[0.333,0.333,0.333],"y":[0,0,0]},"t":25,"s":[0,0,100]},{"i":{"x":[0.667,0.667,0.667],"y":[1,1,1]},"o":{"x":[0.333,0.333,0.333],"y":[0,0,0]},"t":36,"s":[75,75,100]},{"i":{"x":[0.667,0.667,0.667],"y":[1,1,1]},"o":{"x":[0.167,0.167,0.167],"y":[0,0,0]},"t":47,"s":[0,0,100]},{"i":{"x":[0.667,0.667,0.667],"y":[1,1,1]},"o":{"x":[0.333,0.333,0.333],"y":[0,0,0]},"t":58,"s":[75,75,100]},{"i":{"x":[0.667,0.667,0.667],"y":[1,1,1]},"o":{"x":[0.167,0.167,0.167],"y":[0,0,0]},"t":69,"s":[0,0,100]},{"t":82.0000033399285,"s":[75,75,100]}],"ix":6}},"ao":0,"shapes":[{"ty":"gr","it":[{"ind":0,"ty":"sh","ix":1,"ks":{"a":0,"k":{"i":[[-7.126,0],[0,7.127],[7.128,0],[0,-7.127]],"o":[[7.128,0],[0,-7.127],[-7.126,0],[0,7.127]],"v":[[-0.001,12.904],[12.904,0.001],[-0.001,-12.904],[-12.904,0.001]],"c":true},"ix":2},"nm":"Path 1","mn":"ADBE Vector Shape - Group","hd":false},{"ty":"st","c":{"a":0,"k":[0,0,0,1],"ix":3},"o":{"a":0,"k":100,"ix":4},"w":{"a":0,"k":0.7,"ix":5},"lc":2,"lj":2,"bm":0,"nm":"Stroke 1","mn":"ADBE Vector Graphic - Stroke","hd":false},{"ty":"fl","c":{"a":0,"k":[1,1,1,1],"ix":4},"o":{"a":0,"k":100,"ix":5},"r":1,"bm":0,"nm":"Fill 1","mn":"ADBE Vector Graphic - Fill","hd":false},{"ty":"tr","p":{"a":0,"k":[14.653,14.654],"ix":2},"a":{"a":0,"k":[0,0],"ix":1},"s":{"a":0,"k":[100,100],"ix":3},"r":{"a":0,"k":0,"ix":6},"o":{"a":0,"k":100,"ix":7},"sk":{"a":0,"k":0,"ix":4},"sa":{"a":0,"k":0,"ix":5},"nm":"Transform"}],"nm":"Group 1","np":3,"cix":2,"bm":0,"ix":1,"mn":"ADBE Vector Group","hd":false}],"ip":0,"op":150.000006109625,"st":0,"bm":0},{"ddd":0,"ind":11,"ty":4,"nm":"Layer 5 Outlines","parent":1,"sr":1,"ks":{"o":{"a":0,"k":100,"ix":11},"r":{"a":0,"k":0,"ix":10},"p":{"a":0,"k":[53.338,219.659,0],"ix":2},"a":{"a":0,"k":[7.666,7.666,0],"ix":1},"s":{"a":1,"k":[{"i":{"x":[0.667,0.667,0.667],"y":[1,1,1]},"o":{"x":[0.333,0.333,0.333],"y":[0,0,0]},"t":5,"s":[0,0,100]},{"i":{"x":[0.667,0.667,0.667],"y":[1,1,1]},"o":{"x":[0.333,0.333,0.333],"y":[0,0,0]},"t":18,"s":[75,75,100]},{"i":{"x":[0.667,0.667,0.667],"y":[1,1,1]},"o":{"x":[0.333,0.333,0.333],"y":[0,0,0]},"t":31,"s":[0,0,100]},{"i":{"x":[0.667,0.667,0.667],"y":[1,1,1]},"o":{"x":[0.333,0.333,0.333],"y":[0,0,0]},"t":45,"s":[75,75,100]},{"i":{"x":[0.667,0.667,0.667],"y":[1,1,1]},"o":{"x":[0.333,0.333,0.333],"y":[0,0,0]},"t":58,"s":[0,0,100]},{"i":{"x":[0.667,0.667,0.667],"y":[1,1,1]},"o":{"x":[0.333,0.333,0.333],"y":[0,0,0]},"t":70,"s":[75,75,100]},{"t":82.0000033399285,"s":[0,0,100]}],"ix":6}},"ao":0,"shapes":[{"ty":"gr","it":[{"ind":0,"ty":"sh","ix":1,"ks":{"a":0,"k":{"i":[[-3.268,0],[0,3.269],[3.268,0],[0,-3.267]],"o":[[3.268,0],[0,-3.267],[-3.268,0],[0,3.269]],"v":[[-0.001,5.917],[5.917,-0.001],[-0.001,-5.917],[-5.917,-0.001]],"c":true},"ix":2},"nm":"Path 1","mn":"ADBE Vector Shape - Group","hd":false},{"ty":"st","c":{"a":0,"k":[0,0,0,1],"ix":3},"o":{"a":0,"k":100,"ix":4},"w":{"a":0,"k":0.7,"ix":5},"lc":2,"lj":2,"bm":0,"nm":"Stroke 1","mn":"ADBE Vector Graphic - Stroke","hd":false},{"ty":"fl","c":{"a":0,"k":[1,1,1,1],"ix":4},"o":{"a":0,"k":100,"ix":5},"r":1,"bm":0,"nm":"Fill 1","mn":"ADBE Vector Graphic - Fill","hd":false},{"ty":"tr","p":{"a":0,"k":[7.666,7.666],"ix":2},"a":{"a":0,"k":[0,0],"ix":1},"s":{"a":0,"k":[100,100],"ix":3},"r":{"a":0,"k":0,"ix":6},"o":{"a":0,"k":100,"ix":7},"sk":{"a":0,"k":0,"ix":4},"sa":{"a":0,"k":0,"ix":5},"nm":"Transform"}],"nm":"Group 1","np":3,"cix":2,"bm":0,"ix":1,"mn":"ADBE Vector Group","hd":false}],"ip":0,"op":150.000006109625,"st":0,"bm":0},{"ddd":0,"ind":12,"ty":4,"nm":"Layer 6 Outlines","parent":1,"sr":1,"ks":{"o":{"a":0,"k":100,"ix":11},"r":{"a":0,"k":0,"ix":10},"p":{"a":0,"k":[-29.501,336.366,0],"ix":2},"a":{"a":0,"k":[23.899,23.899,0],"ix":1},"s":{"a":1,"k":[{"i":{"x":[0.667,0.667,0.667],"y":[1,1,1]},"o":{"x":[0.333,0.333,0.333],"y":[0,0,0]},"t":5,"s":[0,0,100]},{"i":{"x":[0.667,0.667,0.667],"y":[1,1,1]},"o":{"x":[0.333,0.333,0.333],"y":[0,0,0]},"t":22,"s":[75,75,100]},{"i":{"x":[0.667,0.667,0.667],"y":[1,1,1]},"o":{"x":[0.333,0.333,0.333],"y":[0,0,0]},"t":30,"s":[0,0,100]},{"i":{"x":[0.667,0.667,0.667],"y":[1,1,1]},"o":{"x":[0.333,0.333,0.333],"y":[0,0,0]},"t":42,"s":[75,75,100]},{"i":{"x":[0.667,0.667,0.667],"y":[1,1,1]},"o":{"x":[0.333,0.333,0.333],"y":[0,0,0]},"t":57,"s":[0,0,100]},{"i":{"x":[0.667,0.667,0.667],"y":[1,1,1]},"o":{"x":[0.333,0.333,0.333],"y":[0,0,0]},"t":65,"s":[75,75,100]},{"t":82.0000033399285,"s":[0,0,100]}],"ix":6}},"ao":0,"shapes":[{"ty":"gr","it":[{"ind":0,"ty":"sh","ix":1,"ks":{"a":0,"k":{"i":[[-12.232,0],[0,12.231],[12.232,0],[0,-12.234]],"o":[[12.232,0],[0,-12.234],[-12.232,0],[0,12.231]],"v":[[0,22.149],[22.149,0.001],[0,-22.149],[-22.149,0.001]],"c":true},"ix":2},"nm":"Path 1","mn":"ADBE Vector Shape - Group","hd":false},{"ty":"st","c":{"a":0,"k":[0,0,0,1],"ix":3},"o":{"a":0,"k":100,"ix":4},"w":{"a":0,"k":0.7,"ix":5},"lc":2,"lj":2,"bm":0,"nm":"Stroke 1","mn":"ADBE Vector Graphic - Stroke","hd":false},{"ty":"fl","c":{"a":0,"k":[1,1,1,1],"ix":4},"o":{"a":0,"k":100,"ix":5},"r":1,"bm":0,"nm":"Fill 1","mn":"ADBE Vector Graphic - Fill","hd":false},{"ty":"tr","p":{"a":0,"k":[23.899,23.899],"ix":2},"a":{"a":0,"k":[0,0],"ix":1},"s":{"a":0,"k":[100,100],"ix":3},"r":{"a":0,"k":0,"ix":6},"o":{"a":0,"k":100,"ix":7},"sk":{"a":0,"k":0,"ix":4},"sa":{"a":0,"k":0,"ix":5},"nm":"Transform"}],"nm":"Group 1","np":3,"cix":2,"bm":0,"ix":1,"mn":"ADBE Vector Group","hd":false}],"ip":0,"op":150.000006109625,"st":0,"bm":0},{"ddd":0,"ind":13,"ty":4,"nm":"Layer 7 Outlines","parent":1,"sr":1,"ks":{"o":{"a":0,"k":100,"ix":11},"r":{"a":0,"k":0,"ix":10},"p":{"a":0,"k":[1.756,323.642,0],"ix":2},"a":{"a":0,"k":[38.087,33.314,0],"ix":1},"s":{"a":1,"k":[{"i":{"x":[0.833,0.833,0.833],"y":[1,1,1]},"o":{"x":[0.333,0.333,0.333],"y":[0,0,0]},"t":5,"s":[75,75,100]},{"i":{"x":[0.667,0.667,0.667],"y":[1,1,1]},"o":{"x":[0.167,0.167,0.167],"y":[0,0,0]},"t":17,"s":[61,61,100]},{"i":{"x":[0.833,0.833,0.833],"y":[1,1,1]},"o":{"x":[0.333,0.333,0.333],"y":[0,0,0]},"t":29,"s":[75,75,100]},{"i":{"x":[0.667,0.667,0.667],"y":[1,1,1]},"o":{"x":[0.167,0.167,0.167],"y":[0,0,0]},"t":41,"s":[61,61,100]},{"i":{"x":[0.833,0.833,0.833],"y":[1,1,1]},"o":{"x":[0.333,0.333,0.333],"y":[0,0,0]},"t":52,"s":[75,75,100]},{"i":{"x":[0.667,0.667,0.667],"y":[1,1,1]},"o":{"x":[0.167,0.167,0.167],"y":[0,0,0]},"t":64,"s":[61,61,100]},{"t":82.0000033399285,"s":[75,75,100]}],"ix":6}},"ao":0,"shapes":[{"ty":"gr","it":[{"ind":0,"ty":"sh","ix":1,"ks":{"a":0,"k":{"i":[[0,0],[20.079,0],[0,20.079],[-7.246,6.64]],"o":[[0,20.061],[-20.06,0],[0,-10.602],[0,0]],"v":[[36.338,-4.774],[-0.001,31.564],[-36.338,-4.774],[-24.54,-31.564]],"c":false},"ix":2},"nm":"Path 1","mn":"ADBE Vector Shape - Group","hd":false},{"ty":"st","c":{"a":0,"k":[0,0,0,1],"ix":3},"o":{"a":0,"k":100,"ix":4},"w":{"a":0,"k":0.7,"ix":5},"lc":2,"lj":2,"bm":0,"nm":"Stroke 1","mn":"ADBE Vector Graphic - Stroke","hd":false},{"ty":"fl","c":{"a":0,"k":[1,1,1,1],"ix":4},"o":{"a":0,"k":100,"ix":5},"r":1,"bm":0,"nm":"Fill 1","mn":"ADBE Vector Graphic - Fill","hd":false},{"ty":"tr","p":{"a":0,"k":[38.087,33.314],"ix":2},"a":{"a":0,"k":[0,0],"ix":1},"s":{"a":0,"k":[100,100],"ix":3},"r":{"a":0,"k":0,"ix":6},"o":{"a":0,"k":100,"ix":7},"sk":{"a":0,"k":0,"ix":4},"sa":{"a":0,"k":0,"ix":5},"nm":"Transform"}],"nm":"Group 1","np":3,"cix":2,"bm":0,"ix":1,"mn":"ADBE Vector Group","hd":false}],"ip":0,"op":150.000006109625,"st":0,"bm":0},{"ddd":0,"ind":14,"ty":4,"nm":"Shape Layer 1","parent":1,"sr":1,"ks":{"o":{"a":0,"k":100,"ix":11},"r":{"a":0,"k":0,"ix":10},"p":{"a":0,"k":[0,0,0],"ix":2},"a":{"a":0,"k":[0,0,0],"ix":1},"s":{"a":0,"k":[100,100,100],"ix":6}},"ao":0,"shapes":[],"ip":0,"op":150.000006109625,"st":0,"bm":0},{"ddd":0,"ind":15,"ty":4,"nm":"Layer 1 Outlines","parent":1,"sr":1,"ks":{"o":{"a":0,"k":100,"ix":11},"r":{"a":0,"k":0,"ix":10},"p":{"a":0,"k":[-4.262,295.198,0],"ix":2},"a":{"a":0,"k":[115.128,83.073,0],"ix":1},"s":{"a":1,"k":[{"i":{"x":[0.667,0.667,0.667],"y":[1,1,1]},"o":{"x":[0.333,0.333,0.333],"y":[0,0,0]},"t":5,"s":[75,75,100]},{"i":{"x":[0.667,0.667,0.667],"y":[1,1,1]},"o":{"x":[0.333,0.333,0.333],"y":[0,0,0]},"t":22,"s":[53,53,100]},{"i":{"x":[0.667,0.667,0.667],"y":[1,1,1]},"o":{"x":[0.333,0.333,0.333],"y":[0,0,0]},"t":40,"s":[75,75,100]},{"i":{"x":[0.667,0.667,0.667],"y":[1,1,1]},"o":{"x":[0.333,0.333,0.333],"y":[0,0,0]},"t":58,"s":[53,53,100]},{"t":82.0000033399285,"s":[75,75,100]}],"ix":6}},"ao":0,"shapes":[{"ty":"gr","it":[{"ind":0,"ty":"sh","ix":1,"ks":{"a":0,"k":{"i":[[21.381,0.964],[7.229,-4.784],[6.461,4.069],[0.483,9.443],[21.543,1.463],[0,-24.754],[0,0],[7.478,0.73],[2.41,-0.125],[1.571,-22.703],[-26.253,0],[-7.567,14.671],[-14.796,0],[-2.606,0.536],[-5.265,-5.712],[-12.351,0],[1.696,24.807]],"o":[[-9.406,-0.428],[-3.337,-6.943],[4.712,-7.3],[-1.106,-21.559],[-25.111,-1.695],[0,0],[0.036,7.532],[-2.32,-0.232],[-22.702,1.286],[-1.838,26.628],[17.634,0],[7.104,11.833],[2.749,0],[7.621,-1.534],[7.763,8.407],[24.451,0],[-1.428,-21.328]],"v":[[71.293,-3.561],[45.895,3.453],[30.85,-13.395],[37.649,-38.954],[-2.33,-79.628],[-48.341,-36.705],[-48.341,-36.508],[-61.637,-24.353],[-68.741,-24.497],[-111.54,17.749],[-66.082,66.563],[-25.585,41.861],[9.254,61.601],[17.303,60.797],[38.096,67.633],[69.312,81.323],[111.682,35.865]],"c":true},"ix":2},"nm":"Path 1","mn":"ADBE Vector Shape - Group","hd":false},{"ty":"st","c":{"a":0,"k":[0,0,0,1],"ix":3},"o":{"a":0,"k":100,"ix":4},"w":{"a":0,"k":0.7,"ix":5},"lc":2,"lj":2,"bm":0,"nm":"Stroke 1","mn":"ADBE Vector Graphic - Stroke","hd":false},{"ty":"tr","p":{"a":0,"k":[115.128,83.073],"ix":2},"a":{"a":0,"k":[0,0],"ix":1},"s":{"a":0,"k":[100,100],"ix":3},"r":{"a":0,"k":0,"ix":6},"o":{"a":0,"k":100,"ix":7},"sk":{"a":0,"k":0,"ix":4},"sa":{"a":0,"k":0,"ix":5},"nm":"Transform"}],"nm":"Group 1","np":2,"cix":2,"bm":0,"ix":1,"mn":"ADBE Vector Group","hd":false},{"ty":"gr","it":[{"ind":0,"ty":"sh","ix":1,"ks":{"a":0,"k":{"i":[[21.381,0.964],[7.229,-4.784],[6.461,4.069],[0.483,9.443],[21.543,1.463],[0,-24.754],[0,0],[7.478,0.73],[2.41,-0.125],[1.571,-22.703],[-26.253,0],[-7.567,14.671],[-14.796,0],[-2.606,0.536],[-5.265,-5.712],[-12.351,0],[1.696,24.807]],"o":[[-9.406,-0.428],[-3.337,-6.943],[4.712,-7.3],[-1.106,-21.559],[-25.111,-1.695],[0,0],[0.036,7.532],[-2.32,-0.232],[-22.702,1.286],[-1.838,26.628],[17.634,0],[7.104,11.833],[2.749,0],[7.621,-1.534],[7.763,8.407],[24.451,0],[-1.428,-21.328]],"v":[[71.444,-3.561],[46.046,3.453],[31.001,-13.395],[37.8,-38.954],[-2.179,-79.628],[-48.19,-36.705],[-48.19,-36.508],[-61.486,-24.353],[-68.59,-24.497],[-111.389,17.749],[-65.931,66.563],[-25.434,41.861],[9.405,61.601],[17.454,60.797],[38.247,67.633],[69.463,81.323],[111.833,35.865]],"c":true},"ix":2},"nm":"Path 1","mn":"ADBE Vector Shape - Group","hd":false},{"ty":"fl","c":{"a":0,"k":[1,1,1,1],"ix":4},"o":{"a":0,"k":100,"ix":5},"r":1,"bm":0,"nm":"Fill 1","mn":"ADBE Vector Graphic - Fill","hd":false},{"ty":"tr","p":{"a":0,"k":[114.977,83.073],"ix":2},"a":{"a":0,"k":[0,0],"ix":1},"s":{"a":0,"k":[100,100],"ix":3},"r":{"a":0,"k":0,"ix":6},"o":{"a":0,"k":100,"ix":7},"sk":{"a":0,"k":0,"ix":4},"sa":{"a":0,"k":0,"ix":5},"nm":"Transform"}],"nm":"Group 2","np":4,"cix":2,"bm":0,"ix":2,"mn":"ADBE Vector Group","hd":false}],"ip":0,"op":150.000006109625,"st":0,"bm":0},{"ddd":1,"ind":16,"ty":3,"nm":"Null 4","parent":1,"sr":1,"ks":{"o":{"a":0,"k":0,"ix":11},"rx":{"a":0,"k":0,"ix":8},"ry":{"a":0,"k":0,"ix":9},"rz":{"a":0,"k":0,"ix":10},"or":{"a":0,"k":[0,0,0],"ix":7},"p":{"a":1,"k":[{"i":{"x":0.667,"y":1},"o":{"x":0.333,"y":0},"t":5,"s":[1,-104,0],"to":[0,6.5,0],"ti":[0,0,0]},{"i":{"x":0.667,"y":1},"o":{"x":0.333,"y":0},"t":44,"s":[1,-65,0],"to":[0,0,0],"ti":[0,0,0]},{"i":{"x":0.667,"y":1},"o":{"x":0.333,"y":0},"t":82,"s":[1,-104,0],"to":[0,0,0],"ti":[0,-6.5,0]},{"t":124.000005050624,"s":[1,-65,0]}],"ix":2},"a":{"a":0,"k":[0,0,0],"ix":1},"s":{"a":0,"k":[100,100,100],"ix":6}},"ao":0,"ip":4.00000016292334,"op":150.000006109625,"st":-714.000029081816,"bm":0},{"ddd":0,"ind":17,"ty":4,"nm":"Shape Layer 2","sr":1,"ks":{"o":{"a":0,"k":100,"ix":11},"r":{"a":0,"k":0,"ix":10},"p":{"a":0,"k":[149.5,350,0],"ix":2},"a":{"a":0,"k":[0,0,0],"ix":1},"s":{"a":0,"k":[100,100,100],"ix":6}},"ao":0,"shapes":[{"ty":"gr","it":[{"d":1,"ty":"el","s":{"a":0,"k":[143,37],"ix":2},"p":{"a":0,"k":[0,0],"ix":3},"nm":"Ellipse Path 1","mn":"ADBE Vector Shape - Ellipse","hd":false},{"ty":"st","c":{"a":0,"k":[1,1,1,1],"ix":3},"o":{"a":0,"k":100,"ix":4},"w":{"a":0,"k":0,"ix":5},"lc":1,"lj":1,"ml":4,"bm":0,"nm":"Stroke 1","mn":"ADBE Vector Graphic - Stroke","hd":false},{"ty":"fl","c":{"a":0,"k":[0.694117527382,0.694117527382,0.694117527382,1],"ix":4},"o":{"a":0,"k":100,"ix":5},"r":1,"bm":0,"nm":"Fill 1","mn":"ADBE Vector Graphic - Fill","hd":false},{"ty":"tr","p":{"a":0,"k":[-12.5,263.5],"ix":2},"a":{"a":0,"k":[0,0],"ix":1},"s":{"a":0,"k":[95.415,150.544],"ix":3},"r":{"a":0,"k":0,"ix":6},"o":{"a":0,"k":100,"ix":7},"sk":{"a":0,"k":0,"ix":4},"sa":{"a":0,"k":0,"ix":5},"nm":"Transform"}],"nm":"Ellipse 1","np":3,"cix":2,"bm":0,"ix":1,"mn":"ADBE Vector Group","hd":false}],"ip":0,"op":150.000006109625,"st":0,"bm":0}],"markers":[]}